[
  {
    "id": "bitcoin",
    "symbol": "btc",
    "name": "Bitcoin",
    "image": "https://coin-images.coingecko.com/coins/images/1/large/bitcoin.png?1696501400",
    "current_price": 82544,
    "market_cap": 1638679935075,
    "market_cap_rank": 1,
    "fully_diluted_valuation": 1638679935075,
    "total_volume": 40721668986,
    "high_24h": 84074,
    "low_24h": 80833,
    "price_change_24h": 1610.35,
    "price_change_percentage_24h": 1.9897,
    "market_cap_change_24h": 35570856290,
    "market_cap_change_percentage_24h": 2.21887,
    "circulating_supply": 19835912.0,
    "total_supply": 19835931.0,
    "max_supply": 21000000.0,
    "ath": 108786,
    "ath_change_percentage": -23.94055,
    "ath_date": "2025-01-20T09:11:54.494Z",
    "atl": 67.81,
    "atl_change_percentage": 121921.67523,
    "atl_date": "2013-07-06T00:00:00.000Z",
    "roi": null,
    "last_updated": "2025-03-12T17:39:01.735Z"
  },
  {
    "id": "ethereum",
    "symbol": "eth",
    "name": "Ethereum",
    "image": "https://coin-images.coingecko.com/coins/images/279/large/ethereum.png?1696501628",
    "current_price": 1883.12,
    "market_cap": 227080489410,
    "market_cap_rank": 2,
    "fully_diluted_valuation": 227080489410,
    "total_volume": 25681747927,
    "high_24h": 1958.82,
    "low_24h": 1841.97,
    "price_change_24h": -9.744522455032438,
    "price_change_percentage_24h": -0.5148,
    "market_cap_change_24h": -840921632.7583923,
    "market_cap_change_percentage_24h": -0.36895,
    "circulating_supply": 120609221.7240194,
    "total_supply": 120609221.7240194,
    "max_supply": null,
    "ath": 4878.26,
    "ath_change_percentage": -61.27798,
    "ath_date": "2021-11-10T14:24:19.604Z",
    "atl": 0.432979,
    "atl_change_percentage": 436170.96796,
    "atl_date": "2015-10-20T00:00:00.000Z",
    "roi": {
      "times": 29.485451525148154,
      "currency": "btc",
      "percentage": 2948.5451525148155
    },
    "last_updated": "2025-03-12T17:38:56.558Z"
  },
  {
    "id": "tether",
    "symbol": "usdt",
    "name": "Tether",
    "image": "https://coin-images.coingecko.com/coins/images/325/large/Tether.png?1696501661",
    "current_price": 0.999788,
    "market_cap": 143151854610,
    "market_cap_rank": 3,
    "fully_diluted_valuation": 143151854610,
    "total_volume": 57786111138,
    "high_24h": 0.999873,
    "low_24h": 0.999559,
    "price_change_24h": 0.00017722,
    "price_change_percentage_24h": 0.01773,
    "market_cap_change_24h": 210659626,
    "market_cap_change_percentage_24h": 0.14738,
    "circulating_supply": 143182152538.009,
    "total_supply": 143182152538.009,
    "max_supply": null,
    "ath": 1.32,
    "ath_change_percentage": -24.43922,
    "ath_date": "2018-07-24T00:00:00.000Z",
    "atl": 0.572521,
    "atl_change_percentage": 74.62087,
    "atl_date": "2015-03-02T00:00:00.000Z",
    "roi": null,
    "last_updated": "2025-03-12T17:38:55.807Z"
  },
  {
    "id": "ripple",
    "symbol": "xrp",
    "name": "XRP",
    "image": "https://coin-images.coingecko.com/coins/images/44/large/xrp-symbol-white-128.png?1696501442",
    "current_price": 2.23,
    "market_cap": 129144408983,
    "market_cap_rank": 4,
    "fully_diluted_valuation": 222466339216,
    "total_volume": 5758437476,
    "high_24h": 2.25,
    "low_24h": 2.1,
    "price_change_24h": 0.126134,
    "price_change_percentage_24h": 6.00505,
    "market_cap_change_24h": 7401525095,
    "market_cap_change_percentage_24h": 6.07964,
    "circulating_supply": 58043299826.0,
    "total_supply": 99986368206.0,
    "max_supply": 100000000000.0,
    "ath": 3.4,
    "ath_change_percentage": -34.48868,
    "ath_date": "2018-01-07T00:00:00.000Z",
    "atl": 0.00268621,
    "atl_change_percentage": 82781.53716,
    "atl_date": "2014-05-22T00:00:00.000Z",
    "roi": null,
    "last_updated": "2025-03-12T17:39:01.370Z"
  },
  {
    "id": "binancecoin",
    "symbol": "bnb",
    "name": "BNB",
    "image": "https://coin-images.coingecko.com/coins/images/825/large/bnb-icon2_2x.png?1696501970",
    "current_price": 559.35,
    "market_cap": 81593799687,
    "market_cap_rank": 5,
    "fully_diluted_valuation": 81593799687,
    "total_volume": 1102608297,
    "high_24h": 563.37,
    "low_24h": 545.09,
    "price_change_24h": 12.5,
    "price_change_percentage_24h": 2.28533,
    "market_cap_change_24h": 1814874141,
    "market_cap_change_percentage_24h": 2.27488,
    "circulating_supply": 145887575.79,
    "total_supply": 145887575.79,
    "max_supply": 200000000.0,
    "ath": 788.84,
    "ath_change_percentage": -28.72479,
    "ath_date": "2024-12-04T10:35:25.220Z",
    "atl": 0.0398177,
    "atl_change_percentage": 1411960.37663,
    "atl_date": "2017-10-19T00:00:00.000Z",
    "roi": null,
    "last_updated": "2025-03-12T17:38:52.299Z"
  },
  {
    "id": "solana",
    "symbol": "sol",
    "name": "Solana",
    "image": "https://coin-images.coingecko.com/coins/images/4128/large/solana.png?1718769756",
    "current_price": 125.66,
    "market_cap": 64021546762,
    "market_cap_rank": 6,
    "fully_diluted_valuation": 74908296380,
    "total_volume": 4785081178,
    "high_24h": 129.6,
    "low_24h": 121.33,
    "price_change_24h": 2.05,
    "price_change_percentage_24h": 1.65622,
    "market_cap_change_24h": 1075516290,
    "market_cap_change_percentage_24h": 1.70863,
    "circulating_supply": 509413969.1777073,
    "total_supply": 596038904.2890296,
    "max_supply": null,
    "ath": 293.31,
    "ath_change_percentage": -57.13284,
    "ath_date": "2025-01-19T11:15:27.957Z",
    "atl": 0.500801,
    "atl_change_percentage": 25006.67148,
    "atl_date": "2020-05-11T19:35:23.449Z",
    "roi": null,
    "last_updated": "2025-03-12T17:38:53.197Z"
  },
  {
    "id": "usd-coin",
    "symbol": "usdc",
    "name": "USDC",
    "image": "https://coin-images.coingecko.com/coins/images/6319/large/usdc.png?1696506694",
    "current_price": 0.999849,
    "market_cap": 58116933183,
    "market_cap_rank": 7,
    "fully_diluted_valuation": 58205046454,
    "total_volume": 14580094117,
    "high_24h": 0.999939,
    "low_24h": 0.999787,
    "price_change_24h": -5.00441074469e-7,
    "price_change_percentage_24h": -5.0e-5,
    "market_cap_change_24h": 46508802,
    "market_cap_change_percentage_24h": 0.08009,
    "circulating_supply": 58125770415.4107,
    "total_supply": 58213897084.45434,
    "max_supply": null,
    "ath": 1.17,
    "ath_change_percentage": -14.73769,
    "ath_date": "2019-05-08T00:40:28.300Z",
    "atl": 0.877647,
    "atl_change_percentage": 13.92698,
    "atl_date": "2023-03-11T08:02:13.981Z",
    "roi": null,
    "last_updated": "2025-03-12T17:38:55.564Z"
  },
  {
    "id": "cardano",
    "symbol": "ada",
    "name": "Cardano",
    "image": "https://coin-images.coingecko.com/coins/images/975/large/cardano.png?1696502090",
    "current_price": 0.726083,
    "market_cap": 26167405684,
    "market_cap_rank": 8,
    "fully_diluted_valuation": 32748086471,
    "total_volume": 1328179032,
    "high_24h": 0.761257,
    "low_24h": 0.710094,
    "price_change_24h": 0.01598959,
    "price_change_percentage_24h": 2.25176,
    "market_cap_change_24h": 634189979,
    "market_cap_change_percentage_24h": 2.48378,
    "circulating_supply": 35957314844.72886,
    "total_supply": 45000000000.0,
    "max_supply": 45000000000.0,
    "ath": 3.09,
    "ath_change_percentage": -76.2824,
    "ath_date": "2021-09-02T06:00:10.474Z",
    "atl": 0.01925275,
    "atl_change_percentage": 3702.78899,
    "atl_date": "2020-03-13T02:22:55.044Z",
    "roi": null,
    "last_updated": "2025-03-12T17:38:53.509Z"
  },
  {
    "id": "dogecoin",
    "symbol": "doge",
    "name": "Dogecoin",
    "image": "https://coin-images.coingecko.com/coins/images/5/large/dogecoin.png?1696501409",
    "current_price": 0.167292,
    "market_cap": 24813590504,
    "market_cap_rank": 9,
    "fully_diluted_valuation": 24820069830,
    "total_volume": 1733015719,
    "high_24h": 0.172327,
    "low_24h": 0.15962,
    "price_change_24h": 0.00752507,
    "price_change_percentage_24h": 4.71003,
    "market_cap_change_24h": 1137798587,
    "market_cap_change_percentage_24h": 4.80575,
    "circulating_supply": 148360876383.7051,
    "total_supply": 148400176383.7052,
    "max_supply": null,
    "ath": 0.731578,
    "ath_change_percentage": -77.06317,
    "ath_date": "2021-05-08T05:08:23.458Z",
    "atl": 8.69e-5,
    "atl_change_percentage": 192988.12997,
    "atl_date": "2015-05-06T00:00:00.000Z",
    "roi": null,
    "last_updated": "2025-03-12T17:38:53.737Z"
  },
  {
    "id": "tron",
    "symbol": "trx",
    "name": "TRON",
    "image": "https://coin-images.coingecko.com/coins/images/1094/large/tron-logo.png?1696502193",
    "current_price": 0.223767,
    "market_cap": 21267020939,
    "market_cap_rank": 10,
    "fully_diluted_valuation": 21267029230,
    "total_volume": 961073281,
    "high_24h": 0.227626,
    "low_24h": 0.219733,
    "price_change_24h": -0.000334338894489444,
    "price_change_percentage_24h": -0.14919,
    "market_cap_change_24h": -28801342.23108673,
    "market_cap_change_percentage_24h": -0.13524,
    "circulating_supply": 95032978234.3469,
    "total_supply": 95033015282.67934,
    "max_supply": null,
    "ath": 0.431288,
    "ath_change_percentage": -47.90705,
    "ath_date": "2024-12-04T00:10:40.323Z",
    "atl": 0.00180434,
    "atl_change_percentage": 12351.67872,
    "atl_date": "2017-11-12T00:00:00.000Z",
    "roi": {
      "times": 116.77226746706053,
      "currency": "usd",
      "percentage": 11677.226746706052
    },
    "last_updated": "2025-03-12T17:38:56.089Z"
  },
  {
    "id": "staked-ether",
    "symbol": "steth",
    "name": "Lido Staked Ether",
    "image": "https://coin-images.coingecko.com/coins/images/13442/large/steth_logo.png?1696513206",
    "current_price": 1880.91,
    "market_cap": 17627604857,
    "market_cap_rank": 11,
    "fully_diluted_valuation": 17627604857,
    "total_volume": 144302056,
    "high_24h": 1955.28,
    "low_24h": 1839.26,
    "price_change_24h": -15.12589293179326,
    "price_change_percentage_24h": -0.79776,
    "market_cap_change_24h": -99098904.9983406,
    "market_cap_change_percentage_24h": -0.55904,
    "circulating_supply": 9337854.086762514,
    "total_supply": 9337854.086762514,
    "max_supply": null,
    "ath": 4829.57,
    "ath_change_percentage": -60.93847,
    "ath_date": "2021-11-10T14:40:47.256Z",
    "atl": 482.9,
    "atl_change_percentage": 290.66447,
    "atl_date": "2020-12-22T04:08:21.854Z",
    "roi": null,
    "last_updated": "2025-03-12T17:38:51.935Z"
  },
  {
    "id": "pi-network",
    "symbol": "pi",
    "name": "Pi Network",
    "image": "https://coin-images.coingecko.com/coins/images/54342/large/pi_network.jpg?1739347576",
    "current_price": 1.66,
    "market_cap": 11876327647,
    "market_cap_rank": 12,
    "fully_diluted_valuation": 18271273304,
    "total_volume": 789759591,
    "high_24h": 1.74,
    "low_24h": 1.36,
    "price_change_24h": 0.292861,
    "price_change_percentage_24h": 21.44452,
    "market_cap_change_24h": 2016583843,
    "market_cap_change_percentage_24h": 20.4527,
    "circulating_supply": 7155344217.86878,
    "total_supply": 11008221873.64427,
    "max_supply": 100000000000.0,
    "ath": 2.99,
    "ath_change_percentage": -44.70334,
    "ath_date": "2025-02-26T16:41:03.732Z",
    "atl": 0.615725,
    "atl_change_percentage": 168.30974,
    "atl_date": "2025-02-20T18:06:42.957Z",
    "roi": null,
    "last_updated": "2025-03-12T17:38:59.615Z"
  },
  {
    "id": "wrapped-bitcoin",
    "symbol": "wbtc",
    "name": "Wrapped Bitcoin",
    "image": "https://coin-images.coingecko.com/coins/images/7598/large/wrapped_bitcoin_wbtc.png?1696507857",
    "current_price": 82467,
    "market_cap": 10639231265,
    "market_cap_rank": 13,
    "fully_diluted_valuation": 10639231265,
    "total_volume": 326558327,
    "high_24h": 83821,
    "low_24h": 80603,
    "price_change_24h": 1722.92,
    "price_change_percentage_24h": 2.13381,
    "market_cap_change_24h": 235643798,
    "market_cap_change_percentage_24h": 2.26502,
    "circulating_supply": 129015.15657878,
    "total_supply": 129015.15657878,
    "max_supply": 129015.15657878,
    "ath": 108368,
    "ath_change_percentage": -23.7817,
    "ath_date": "2025-01-20T07:16:27.137Z",
    "atl": 3139.17,
    "atl_change_percentage": 2531.14321,
    "atl_date": "2019-04-02T00:00:00.000Z",
    "roi": null,
    "last_updated": "2025-03-12T17:38:56.193Z"
  },
  {
    "id": "lombard-staked-btc",
    "symbol": "lbtc",
    "name": "Lombard Staked BTC",
    "image": "https://coin-images.coingecko.com/coins/images/39969/large/LBTC_Logo.png?1724959872",
    "current_price": 82553,
    "market_cap": 9854317885,
    "market_cap_rank": 14,
    "fully_diluted_valuation": 9854317885,
    "total_volume": 3376011,
    "high_24h": 83890,
    "low_24h": 80728,
    "price_change_24h": 1749.4,
    "price_change_percentage_24h": 2.165,
    "market_cap_change_24h": 6189682265,
    "market_cap_change_percentage_24h": 168.90308,
    "circulating_supply": 119111.27163082,
    "total_supply": 119111.27163082,
    "max_supply": null,
    "ath": 114576,
    "ath_change_percentage": -27.89723,
    "ath_date": "2025-02-04T01:47:44.052Z",
    "atl": 52119,
    "atl_change_percentage": 58.50586,
    "atl_date": "2024-09-06T21:01:52.094Z",
    "roi": null,
    "last_updated": "2025-03-12T17:38:57.669Z"
  },
  {
    "id": "leo-token",
    "symbol": "leo",
    "name": "LEO Token",
    "image": "https://coin-images.coingecko.com/coins/images/8418/large/leo-token.png?1696508607",
    "current_price": 9.68,
    "market_cap": 8943957926,
    "market_cap_rank": 15,
    "fully_diluted_valuation": 9537229544,
    "total_volume": 4269635,
    "high_24h": 9.93,
    "low_24h": 9.61,
    "price_change_24h": -0.1232936912701863,
    "price_change_percentage_24h": -1.25795,
    "market_cap_change_24h": -99236126.26462936,
    "market_cap_change_percentage_24h": -1.09736,
    "circulating_supply": 923951827.9,
    "total_supply": 985239504.0,
    "max_supply": null,
    "ath": 10.14,
    "ath_change_percentage": -4.19004,
    "ath_date": "2025-03-10T09:26:43.294Z",
    "atl": 0.799859,
    "atl_change_percentage": 1114.01927,
    "atl_date": "2019-12-24T15:14:35.376Z",
    "roi": null,
    "last_updated": "2025-03-12T17:38:56.943Z"
  },
  {
    "id": "chainlink",
    "symbol": "link",
    "name": "Chainlink",
    "image": "https://coin-images.coingecko.com/coins/images/877/large/chainlink-new-logo.png?1696502009",
    "current_price": 13.26,
    "market_cap": 8460945330,
    "market_cap_rank": 16,
    "fully_diluted_valuation": 13259592105,
    "total_volume": 749575145,
    "high_24h": 13.74,
    "low_24h": 12.67,
    "price_change_24h": 0.387126,
    "price_change_percentage_24h": 3.00741,
    "market_cap_change_24h": 229331454,
    "market_cap_change_percentage_24h": 2.78598,
    "circulating_supply": 638099970.4505637,
    "total_supply": 1000000000.0,
    "max_supply": 1000000000.0,
    "ath": 52.7,
    "ath_change_percentage": -74.73979,
    "ath_date": "2021-05-10T00:13:57.214Z",
    "atl": 0.148183,
    "atl_change_percentage": 8882.98463,
    "atl_date": "2017-11-29T00:00:00.000Z",
    "roi": null,
    "last_updated": "2025-03-12T17:38:53.633Z"
  },
  {
    "id": "hedera-hashgraph",
    "symbol": "hbar",
    "name": "Hedera",
    "image": "https://coin-images.coingecko.com/coins/images/3688/large/hbar.png?1696504364",
    "current_price": 0.19949,
    "market_cap": 8433280542,
    "market_cap_rank": 17,
    "fully_diluted_valuation": 9987877537,
    "total_volume": 626180517,
    "high_24h": 0.213726,
    "low_24h": 0.191594,
    "price_change_24h": 0.00789678,
    "price_change_percentage_24h": 4.12163,
    "market_cap_change_24h": 364614049,
    "market_cap_change_percentage_24h": 4.51889,
    "circulating_supply": 42217580818.57279,
    "total_supply": 50000000000.0,
    "max_supply": 50000000000.0,
    "ath": 0.569229,
    "ath_change_percentage": -64.80401,
    "ath_date": "2021-09-15T10:40:28.318Z",
    "atl": 0.00986111,
    "atl_change_percentage": 1931.6757,
    "atl_date": "2020-01-02T17:30:24.852Z",
    "roi": null,
    "last_updated": "2025-03-12T17:38:56.415Z"
  },
  {
    "id": "usds",
    "symbol": "usds",
    "name": "USDS",
    "image": "https://coin-images.coingecko.com/coins/images/39926/large/usds.webp?1726666683",
    "current_price": 1.0,
    "market_cap": 8107438434,
    "market_cap_rank": 18,
    "fully_diluted_valuation": 8107438434,
    "total_volume": 36741595,
    "high_24h": 1.002,
    "low_24h": 0.998257,
    "price_change_24h": 5.305e-5,
    "price_change_percentage_24h": 0.00531,
    "market_cap_change_24h": -82122822.40130138,
    "market_cap_change_percentage_24h": -1.00277,
    "circulating_supply": 8112573385.037609,
    "total_supply": 8110395395.413195,
    "max_supply": null,
    "ath": 1.057,
    "ath_change_percentage": -5.4617,
    "ath_date": "2024-10-29T05:40:51.197Z",
    "atl": 0.948265,
    "atl_change_percentage": 5.41086,
    "atl_date": "2024-10-03T13:19:28.826Z",
    "roi": null,
    "last_updated": "2025-03-12T17:38:54.713Z"
  },
  {
    "id": "stellar",
    "symbol": "xlm",
    "name": "Stellar",
    "image": "https://coin-images.coingecko.com/coins/images/100/large/fmpFRHHQ_400x400.jpg?1735231350",
    "current_price": 0.256678,
    "market_cap": 7882078811,
    "market_cap_rank": 19,
    "fully_diluted_valuation": 12831487083,
    "total_volume": 256343662,
    "high_24h": 0.262067,
    "low_24h": 0.248224,
    "price_change_24h": 0.00654469,
    "price_change_percentage_24h": 2.61649,
    "market_cap_change_24h": 177136066,
    "market_cap_change_percentage_24h": 2.29899,
    "circulating_supply": 30714914216.47261,
    "total_supply": 50001786894.44301,
    "max_supply": 50001786894.44301,
    "ath": 0.875563,
    "ath_change_percentage": -70.64686,
    "ath_date": "2018-01-03T00:00:00.000Z",
    "atl": 0.00047612,
    "atl_change_percentage": 53878.69769,
    "atl_date": "2015-03-05T00:00:00.000Z",
    "roi": null,
    "last_updated": "2025-03-12T17:38:52.651Z"
  },
  {
    "id": "wrapped-steth",
    "symbol": "wsteth",
    "name": "Wrapped stETH",
    "image": "https://coin-images.coingecko.com/coins/images/18834/large/wstETH.png?1696518295",
    "current_price": 2249.55,
    "market_cap": 7873582467,
    "market_cap_rank": 20,
    "fully_diluted_valuation": 7873582467,
    "total_volume": 42774096,
    "high_24h": 2339.52,
    "low_24h": 2197.21,
    "price_change_24h": -35.138597458356344,
    "price_change_percentage_24h": -1.53801,
    "market_cap_change_24h": -67501737.2839508,
    "market_cap_change_percentage_24h": -0.85003,
    "circulating_supply": 3492732.112703885,
    "total_supply": 3491647.693571137,
    "max_supply": null,
    "ath": 7256.02,
    "ath_change_percentage": -68.96357,
    "ath_date": "2022-05-13T15:09:54.509Z",
    "atl": 558.54,
    "atl_change_percentage": 303.19574,
    "atl_date": "2022-05-13T01:36:45.053Z",
    "roi": null,
    "last_updated": "2025-03-12T17:38:55.770Z"
  },
  {
    "id": "avalanche-2",
    "symbol": "avax",
    "name": "Avalanche",
    "image": "https://coin-images.coingecko.com/coins/images/12559/large/Avalanche_Circle_RedWhite_Trans.png?1696512369",
    "current_price": 18.33,
    "market_cap": 7601887090,
    "market_cap_rank": 21,
    "fully_diluted_valuation": 8274684791,
    "total_volume": 493994624,
    "high_24h": 18.76,
    "low_24h": 16.97,
    "price_change_24h": 1.26,
    "price_change_percentage_24h": 7.36789,
    "market_cap_change_24h": 539774844,
    "market_cap_change_percentage_24h": 7.64325,
    "circulating_supply": 414324965.0324479,
    "total_supply": 450994397.3314513,
    "max_supply": 720000000.0,
    "ath": 144.96,
    "ath_change_percentage": -87.23103,
    "ath_date": "2021-11-21T14:18:56.538Z",
    "atl": 2.8,
    "atl_change_percentage": 560.82227,
    "atl_date": "2020-12-31T13:15:21.540Z",
    "roi": null,
    "last_updated": "2025-03-12T17:39:01.269Z"
  },
  {
    "id": "shiba-inu",
    "symbol": "shib",
    "name": "Shiba Inu",
    "image": "https://coin-images.coingecko.com/coins/images/11939/large/shiba.png?1696511800",
    "current_price": 1.223e-5,
    "market_cap": 7209161538,
    "market_cap_rank": 22,
    "fully_diluted_valuation": 7212262386,
    "total_volume": 267346555,
    "high_24h": 1.256e-5,
    "low_24h": 1.174e-5,
    "price_change_24h": 4.9242e-7,
    "price_change_percentage_24h": 4.19351,
    "market_cap_change_24h": 297759878,
    "market_cap_change_percentage_24h": 4.30824,
    "circulating_supply": 589253494766181.5,
    "total_supply": 589506948025511.1,
    "max_supply": null,
    "ath": 8.616e-5,
    "ath_change_percentage": -85.77108,
    "ath_date": "2021-10-28T03:54:55.568Z",
    "atl": 5.6366e-11,
    "atl_change_percentage": 21749502.08218,
    "atl_date": "2020-11-28T11:26:25.838Z",
    "roi": null,
    "last_updated": "2025-03-12T17:39:00.029Z"
  },
  {
    "id": "sui",
    "symbol": "sui",
    "name": "Sui",
    "image": "https://coin-images.coingecko.com/coins/images/26375/large/sui-ocean-square.png?1727791290",
    "current_price": 2.25,
    "market_cap": 7136013489,
    "market_cap_rank": 23,
    "fully_diluted_valuation": 22512183979,
    "total_volume": 1056714723,
    "high_24h": 2.36,
    "low_24h": 2.16,
    "price_change_24h": 0.088535,
    "price_change_percentage_24h": 4.09793,
    "market_cap_change_24h": 287259028,
    "market_cap_change_percentage_24h": 4.19433,
    "circulating_supply": 3169845047.483887,
    "total_supply": 10000000000.0,
    "max_supply": 10000000000.0,
    "ath": 5.35,
    "ath_change_percentage": -57.64392,
    "ath_date": "2025-01-04T22:56:18.063Z",
    "atl": 0.364846,
    "atl_change_percentage": 520.69873,
    "atl_date": "2023-10-19T10:40:30.078Z",
    "roi": null,
    "last_updated": "2025-03-12T17:38:54.551Z"
  },
  {
    "id": "bitcoin-cash",
    "symbol": "bch",
    "name": "Bitcoin Cash",
    "image": "https://coin-images.coingecko.com/coins/images/780/large/bitcoin-cash-circle.png?1696501932",
    "current_price": 353.42,
    "market_cap": 7017372228,
    "market_cap_rank": 24,
    "fully_diluted_valuation": 7017398754,
    "total_volume": 297000502,
    "high_24h": 356.94,
    "low_24h": 331.84,
    "price_change_24h": 19.36,
    "price_change_percentage_24h": 5.79508,
    "market_cap_change_24h": 389493442,
    "market_cap_change_percentage_24h": 5.87659,
    "circulating_supply": 19841178.02165078,
    "total_supply": 19841253.02165078,
    "max_supply": 21000000.0,
    "ath": 3785.82,
    "ath_change_percentage": -90.59398,
    "ath_date": "2017-12-20T00:00:00.000Z",
    "atl": 76.93,
    "atl_change_percentage": 362.85297,
    "atl_date": "2018-12-16T00:00:00.000Z",
    "roi": null,
    "last_updated": "2025-03-12T17:38:51.936Z"
  },
  {
    "id": "litecoin",
    "symbol": "ltc",
    "name": "Litecoin",
    "image": "https://coin-images.coingecko.com/coins/images/2/large/litecoin.png?1696501400",
    "current_price": 90.76,
    "market_cap": 6860172893,
    "market_cap_rank": 25,
    "fully_diluted_valuation": 6860259070,
    "total_volume": 641706221,
    "high_24h": 93.02,
    "low_24h": 87.72,
    "price_change_24h": 0.66654,
    "price_change_percentage_24h": 0.7398,
    "market_cap_change_24h": 59932784,
    "market_cap_change_percentage_24h": 0.88133,
    "circulating_supply": 75625345.73347135,
    "total_supply": 75626295.73347135,
    "max_supply": 84000000.0,
    "ath": 410.26,
    "ath_change_percentage": -77.81886,
    "ath_date": "2021-05-10T03:13:07.904Z",
    "atl": 1.15,
    "atl_change_percentage": 7821.04295,
    "atl_date": "2015-01-14T00:00:00.000Z",
    "roi": null,
    "last_updated": "2025-03-12T17:38:59.294Z"
  },
  {
    "id": "the-open-network",
    "symbol": "ton",
    "name": "Toncoin",
    "image": "https://coin-images.coingecko.com/coins/images/17980/large/photo_2024-09-10_17.09.00.jpeg?1725963446",
    "current_price": 2.73,
    "market_cap": 6771950431,
    "market_cap_rank": 26,
    "fully_diluted_valuation": 13986926197,
    "total_volume": 193715931,
    "high_24h": 2.74,
    "low_24h": 2.59,
    "price_change_24h": 0.108475,
    "price_change_percentage_24h": 4.13817,
    "market_cap_change_24h": 262026294,
    "market_cap_change_percentage_24h": 4.02503,
    "circulating_supply": 2481064778.241226,
    "total_supply": 5124442403.682796,
    "max_supply": null,
    "ath": 8.25,
    "ath_change_percentage": -66.82324,
    "ath_date": "2024-06-15T00:36:51.509Z",
    "atl": 0.519364,
    "atl_change_percentage": 427.2372,
    "atl_date": "2021-09-21T00:33:11.092Z",
    "roi": null,
    "last_updated": "2025-03-12T17:38:56.613Z"
  },
  {
    "id": "polkadot",
    "symbol": "dot",
    "name": "Polkadot",
    "image": "https://coin-images.coingecko.com/coins/images/12171/large/polkadot.png?1696512008",
    "current_price": 3.96,
    "market_cap": 6038533671,
    "market_cap_rank": 27,
    "fully_diluted_valuation": 6038533671,
    "total_volume": 218954444,
    "high_24h": 4.12,
    "low_24h": 3.87,
    "price_change_24h": 0.01297663,
    "price_change_percentage_24h": 0.32842,
    "market_cap_change_24h": 30635833,
    "market_cap_change_percentage_24h": 0.50993,
    "circulating_supply": 1522267060.0,
    "total_supply": 1522267060.0,
    "max_supply": null,
    "ath": 54.98,
    "ath_change_percentage": -92.75514,
    "ath_date": "2021-11-04T14:10:09.301Z",
    "atl": 2.7,
    "atl_change_percentage": 47.66835,
    "atl_date": "2020-08-20T05:48:11.359Z",
    "roi": null,
    "last_updated": "2025-03-12T17:39:01.056Z"
  },
  {
    "id": "ethena-usde",
    "symbol": "usde",
    "name": "Ethena USDe",
    "image": "https://coin-images.coingecko.com/coins/images/33613/large/usde.png?1733810059",
    "current_price": 0.999318,
    "market_cap": 5450941613,
    "market_cap_rank": 28,
    "fully_diluted_valuation": 5450966354,
    "total_volume": 75201066,
    "high_24h": 1.001,
    "low_24h": 0.9985,
    "price_change_24h": 7.816e-5,
    "price_change_percentage_24h": 0.00782,
    "market_cap_change_24h": 967070,
    "market_cap_change_percentage_24h": 0.01774,
    "circulating_supply": 5454870045.204523,
    "total_supply": 5454894804.167823,
    "max_supply": null,
    "ath": 1.032,
    "ath_change_percentage": -3.18264,
    "ath_date": "2023-12-20T15:38:34.596Z",
    "atl": 0.929486,
    "atl_change_percentage": 7.504,
    "atl_date": "2024-10-04T07:57:15.809Z",
    "roi": null,
    "last_updated": "2025-03-12T17:38:54.118Z"
  },
  {
    "id": "weth",
    "symbol": "weth",
    "name": "WETH",
    "image": "https://coin-images.coingecko.com/coins/images/2518/large/weth.png?1696503332",
    "current_price": 1881.84,
    "market_cap": 5289310244,
    "market_cap_rank": 29,
    "fully_diluted_valuation": 5289310244,
    "total_volume": 459515319,
    "high_24h": 1956.97,
    "low_24h": 1840.05,
    "price_change_24h": -9.548699094221547,
    "price_change_percentage_24h": -0.50485,
    "market_cap_change_24h": -24880817.052827835,
    "market_cap_change_percentage_24h": -0.4682,
    "circulating_supply": 2812707.430138878,
    "total_supply": 2812880.893797936,
    "max_supply": null,
    "ath": 4799.89,
    "ath_change_percentage": -60.64305,
    "ath_date": "2021-11-09T00:00:00.000Z",
    "atl": 82.1,
    "atl_change_percentage": 2200.8687,
    "atl_date": "2018-12-15T00:00:00.000Z",
    "roi": null,
    "last_updated": "2025-03-12T17:38:55.801Z"
  },
  {
    "id": "binance-bridged-usdt-bnb-smart-chain",
    "symbol": "bsc-usd",
    "name": "Binance Bridged USDT (BNB Smart Chain)",
    "image": "https://coin-images.coingecko.com/coins/images/35021/large/USDT.png?1707233575",
    "current_price": 0.999674,
    "market_cap": 5189919289,
    "market_cap_rank": 30,
    "fully_diluted_valuation": 5189919289,
    "total_volume": 354893076,
    "high_24h": 1.004,
    "low_24h": 0.986014,
    "price_change_24h": -0.001215584360880428,
    "price_change_percentage_24h": -0.12145,
    "market_cap_change_24h": -1850706.8470945358,
    "market_cap_change_percentage_24h": -0.03565,
    "circulating_supply": 5184994501.618546,
    "total_supply": 5184994501.618546,
    "max_supply": null,
    "ath": 1.05,
    "ath_change_percentage": -5.01293,
    "ath_date": "2024-08-05T14:21:42.527Z",
    "atl": 0.942186,
    "atl_change_percentage": 5.85248,
    "atl_date": "2024-12-05T22:30:39.827Z",
    "roi": null,
    "last_updated": "2025-03-12T17:38:54.671Z"
  },
  {
    "id": "bitget-token",
    "symbol": "bgb",
    "name": "Bitget Token",
    "image": "https://coin-images.coingecko.com/coins/images/11610/large/Bitget_logo.png?1736925727",
    "current_price": 4.2,
    "market_cap": 5034163258,
    "market_cap_rank": 31,
    "fully_diluted_valuation": 5034163258,
    "total_volume": 233698079,
    "high_24h": 4.24,
    "low_24h": 4.11,
    "price_change_24h": 0.068755,
    "price_change_percentage_24h": 1.66622,
    "market_cap_change_24h": 82800791,
    "market_cap_change_percentage_24h": 1.67228,
    "circulating_supply": 1199999994.2,
    "total_supply": 1199999994.2,
    "max_supply": 2000000000.0,
    "ath": 8.45,
    "ath_change_percentage": -50.37296,
    "ath_date": "2024-12-27T11:41:24.992Z",
    "atl": 0.0142795,
    "atl_change_percentage": 29268.29253,
    "atl_date": "2020-06-25T04:17:05.895Z",
    "roi": null,
    "last_updated": "2025-03-12T17:38:50.669Z"
  },
  {
    "id": "hyperliquid",
    "symbol": "hype",
    "name": "Hyperliquid",
    "image": "https://coin-images.coingecko.com/coins/images/50882/large/hyperliquid.jpg?1729431300",
    "current_price": 13.32,
    "market_cap": 4469501950,
    "market_cap_rank": 32,
    "fully_diluted_valuation": 13384491846,
    "total_volume": 201946889,
    "high_24h": 14.73,
    "low_24h": 12.71,
    "price_change_24h": -0.5990752795958159,
    "price_change_percentage_24h": -4.30326,
    "market_cap_change_24h": -265941327.00578213,
    "market_cap_change_percentage_24h": -5.61598,
    "circulating_supply": 333928180.0,
    "total_supply": 999990391.0,
    "max_supply": 1000000000.0,
    "ath": 34.96,
    "ath_change_percentage": -61.79193,
    "ath_date": "2024-12-22T03:56:00.276Z",
    "atl": 3.81,
    "atl_change_percentage": 250.70076,
    "atl_date": "2024-11-29T09:30:30.871Z",
    "roi": null,
    "last_updated": "2025-03-12T17:38:56.639Z"
  },
  {
    "id": "whitebit",
    "symbol": "wbt",
    "name": "WhiteBIT Coin",
    "image": "https://coin-images.coingecko.com/coins/images/27045/large/wbt_token.png?1696526096",
    "current_price": 28.75,
    "market_cap": 4143984253,
    "market_cap_rank": 33,
    "fully_diluted_valuation": 9466669004,
    "total_volume": 78827837,
    "high_24h": 29.32,
    "low_24h": 28.66,
    "price_change_24h": -0.20967959006032544,
    "price_change_percentage_24h": -0.72393,
    "market_cap_change_24h": -21441934.52239752,
    "market_cap_change_percentage_24h": -0.51476,
    "circulating_supply": 144118517.10815412,
    "total_supply": 329229605.0,
    "max_supply": 400000000.0,
    "ath": 31.28,
    "ath_change_percentage": -7.95034,
    "ath_date": "2025-03-02T22:22:36.852Z",
    "atl": 3.06,
    "atl_change_percentage": 840.29463,
    "atl_date": "2023-02-13T19:01:21.899Z",
    "roi": null,
    "last_updated": "2025-03-12T17:38:55.294Z"
  },
  {
    "id": "wrapped-eeth",
    "symbol": "weeth",
    "name": "Wrapped eETH",
    "image": "https://coin-images.coingecko.com/coins/images/33033/large/weETH.png?1701438396",
    "current_price": 1998.82,
    "market_cap": 3835933190,
    "market_cap_rank": 34,
    "fully_diluted_valuation": 3835932480,
    "total_volume": 22005049,
    "high_24h": 2081.65,
    "low_24h": 1956.78,
    "price_change_24h": -11.413759182629747,
    "price_change_percentage_24h": -0.56778,
    "market_cap_change_24h": -45814878.32486582,
    "market_cap_change_percentage_24h": -1.18026,
    "circulating_supply": 1916033.592129507,
    "total_supply": 1916033.237195807,
    "max_supply": null,
    "ath": 4311.81,
    "ath_change_percentage": -53.52853,
    "ath_date": "2024-12-06T20:32:25.758Z",
    "atl": 1889.13,
    "atl_change_percentage": 6.06792,
    "atl_date": "2025-03-11T00:55:51.837Z",
    "roi": null,
    "last_updated": "2025-03-12T17:38:55.367Z"
  },
  {
    "id": "monero",
    "symbol": "xmr",
    "name": "Monero",
    "image": "https://coin-images.coingecko.com/coins/images/69/large/monero_logo.png?1696501460",
    "current_price": 207.78,
    "market_cap": 3833492014,
    "market_cap_rank": 35,
    "fully_diluted_valuation": 3833492014,
    "total_volume": 57365343,
    "high_24h": 213.2,
    "low_24h": 204.41,
    "price_change_24h": 3.37,
    "price_change_percentage_24h": 1.65045,
    "market_cap_change_24h": 69444081,
    "market_cap_change_percentage_24h": 1.84493,
    "circulating_supply": 18446744.07370955,
    "total_supply": 18446744.07370955,
    "max_supply": null,
    "ath": 542.33,
    "ath_change_percentage": -61.64565,
    "ath_date": "2018-01-09T00:00:00.000Z",
    "atl": 0.216177,
    "atl_change_percentage": 96120.09882,
    "atl_date": "2015-01-14T00:00:00.000Z",
    "roi": null,
    "last_updated": "2025-03-12T17:38:58.182Z"
  },
  {
    "id": "susds",
    "symbol": "susds",
    "name": "sUSDS",
    "image": "https://coin-images.coingecko.com/coins/images/52721/large/sUSDS_Coin.png?1734086971",
    "current_price": 1.042,
    "market_cap": 3545763128,
    "market_cap_rank": 36,
    "fully_diluted_valuation": 3545763128,
    "total_volume": 2832506,
    "high_24h": 1.045,
    "low_24h": 1.041,
    "price_change_24h": 0.00060626,
    "price_change_percentage_24h": 0.05822,
    "market_cap_change_24h": 144009687,
    "market_cap_change_percentage_24h": 4.2334,
    "circulating_supply": 3401109140.141132,
    "total_supply": 3315157013.533691,
    "max_supply": null,
    "ath": 1.088,
    "ath_change_percentage": -4.14715,
    "ath_date": "2025-02-03T02:31:35.208Z",
    "atl": 0.961716,
    "atl_change_percentage": 8.43086,
    "atl_date": "2025-01-04T01:21:08.460Z",
    "roi": null,
    "last_updated": "2025-03-12T17:38:53.154Z"
  },
  {
    "id": "uniswap",
    "symbol": "uni",
    "name": "Uniswap",
    "image": "https://coin-images.coingecko.com/coins/images/12504/large/uniswap-logo.png?1720676669",
    "current_price": 5.85,
    "market_cap": 3510366976,
    "market_cap_rank": 37,
    "fully_diluted_valuation": 5845904955,
    "total_volume": 218318905,
    "high_24h": 6.23,
    "low_24h": 5.77,
    "price_change_24h": -0.06553695239396529,
    "price_change_percentage_24h": -1.10871,
    "market_cap_change_24h": -32839792.945869923,
    "market_cap_change_percentage_24h": -0.92684,
    "circulating_supply": 600483073.71,
    "total_supply": 1000000000.0,
    "max_supply": 1000000000.0,
    "ath": 44.92,
    "ath_change_percentage": -86.91636,
    "ath_date": "2021-05-03T05:25:04.822Z",
    "atl": 1.03,
    "atl_change_percentage": 470.47974,
    "atl_date": "2020-09-17T01:20:38.214Z",
    "roi": null,
    "last_updated": "2025-03-12T17:38:55.953Z"
  },
  {
    "id": "dai",
    "symbol": "dai",
    "name": "Dai",
    "image": "https://coin-images.coingecko.com/coins/images/9956/large/Badge_Dai.png?1696509996",
    "current_price": 0.999853,
    "market_cap": 3216636765,
    "market_cap_rank": 38,
    "fully_diluted_valuation": 3218151893,
    "total_volume": 127587486,
    "high_24h": 1.001,
    "low_24h": 0.999081,
    "price_change_24h": 0.00036143,
    "price_change_percentage_24h": 0.03616,
    "market_cap_change_24h": 4914685,
    "market_cap_change_percentage_24h": 0.15302,
    "circulating_supply": 3217110189.482536,
    "total_supply": 3218625540.990275,
    "max_supply": null,
    "ath": 1.22,
    "ath_change_percentage": -17.98907,
    "ath_date": "2020-03-13T03:02:50.373Z",
    "atl": 0.88196,
    "atl_change_percentage": 13.34487,
    "atl_date": "2023-03-11T07:50:50.514Z",
    "roi": null,
    "last_updated": "2025-03-12T17:38:53.449Z"
  },
  {
    "id": "aptos",
    "symbol": "apt",
    "name": "Aptos",
    "image": "https://coin-images.coingecko.com/coins/images/26455/large/aptos_round.png?1696525528",
    "current_price": 5.14,
    "market_cap": 3030660149,
    "market_cap_rank": 39,
    "fully_diluted_valuation": 5869855290,
    "total_volume": 216339457,
    "high_24h": 5.61,
    "low_24h": 5.04,
    "price_change_24h": -0.275308614712201,
    "price_change_percentage_24h": -5.0868,
    "market_cap_change_24h": -175392883.36266327,
    "market_cap_change_percentage_24h": -5.47068,
    "circulating_supply": 590639391.5721234,
    "total_supply": 1143965835.429071,
    "max_supply": null,
    "ath": 19.92,
    "ath_change_percentage": -74.15459,
    "ath_date": "2023-01-26T14:25:17.390Z",
    "atl": 3.08,
    "atl_change_percentage": 67.17049,
    "atl_date": "2022-12-29T21:35:14.796Z",
    "roi": null,
    "last_updated": "2025-03-12T17:38:59.551Z"
  },
  {
    "id": "near",
    "symbol": "near",
    "name": "NEAR Protocol",
    "image": "https://coin-images.coingecko.com/coins/images/10365/large/near.jpg?1696510367",
    "current_price": 2.52,
    "market_cap": 3002661456,
    "market_cap_rank": 40,
    "fully_diluted_valuation": 3127028676,
    "total_volume": 254718034,
    "high_24h": 2.55,
    "low_24h": 2.35,
    "price_change_24h": 0.082131,
    "price_change_percentage_24h": 3.3659,
    "market_cap_change_24h": 103000008,
    "market_cap_change_percentage_24h": 3.55214,
    "circulating_supply": 1190307900.0,
    "total_supply": 1239609257.0,
    "max_supply": null,
    "ath": 20.44,
    "ath_change_percentage": -87.55145,
    "ath_date": "2022-01-16T22:09:45.873Z",
    "atl": 0.526762,
    "atl_change_percentage": 382.99739,
    "atl_date": "2020-11-04T16:09:15.137Z",
    "roi": null,
    "last_updated": "2025-03-12T17:38:59.132Z"
  },
  {
    "id": "pepe",
    "symbol": "pepe",
    "name": "Pepe",
    "image": "https://coin-images.coingecko.com/coins/images/29850/large/pepe-token.jpeg?1696528776",
    "current_price": 6.64e-6,
    "market_cap": 2793012547,
    "market_cap_rank": 41,
    "fully_diluted_valuation": 2793012547,
    "total_volume": 1004531347,
    "high_24h": 6.78e-6,
    "low_24h": 6.03e-6,
    "price_change_24h": 6.14333e-7,
    "price_change_percentage_24h": 10.19449,
    "market_cap_change_24h": 256141104,
    "market_cap_change_percentage_24h": 10.09673,
    "circulating_supply": 420690000000000.0,
    "total_supply": 420690000000000.0,
    "max_supply": 420690000000000.0,
    "ath": 2.803e-5,
    "ath_change_percentage": -76.20896,
    "ath_date": "2024-12-09T16:30:35.828Z",
    "atl": 5.5142e-8,
    "atl_change_percentage": 11992.68766,
    "atl_date": "2023-04-18T02:14:41.591Z",
    "roi": null,
    "last_updated": "2025-03-12T17:38:59.482Z"
  },
  {
    "id": "ethereum-classic",
    "symbol": "etc",
    "name": "Ethereum Classic",
    "image": "https://coin-images.coingecko.com/coins/images/453/large/ethereum-classic-logo.png?1696501717",
    "current_price": 17.9,
    "market_cap": 2702761303,
    "market_cap_rank": 42,
    "fully_diluted_valuation": 2702761303,
    "total_volume": 82735642,
    "high_24h": 18.12,
    "low_24h": 17.25,
    "price_change_24h": 0.322031,
    "price_change_percentage_24h": 1.83196,
    "market_cap_change_24h": 52775570,
    "market_cap_change_percentage_24h": 1.99154,
    "circulating_supply": 151088866.8074495,
    "total_supply": 151089423.4154495,
    "max_supply": 210700000.0,
    "ath": 167.09,
    "ath_change_percentage": -89.25263,
    "ath_date": "2021-05-06T18:34:22.133Z",
    "atl": 0.615038,
    "atl_change_percentage": 2819.70397,
    "atl_date": "2016-07-25T00:00:00.000Z",
    "roi": {
      "times": 38.77893668622304,
      "currency": "usd",
      "percentage": 3877.8936686223046
    },
    "last_updated": "2025-03-12T17:38:56.116Z"
  },
  {
    "id": "ondo-finance",
    "symbol": "ondo",
    "name": "Ondo",
    "image": "https://coin-images.coingecko.com/coins/images/26580/large/ONDO.png?1696525656",
    "current_price": 0.851266,
    "market_cap": 2688342436,
    "market_cap_rank": 43,
    "fully_diluted_valuation": 8509816179,
    "total_volume": 254690623,
    "high_24h": 0.892089,
    "low_24h": 0.799123,
    "price_change_24h": 0.051942,
    "price_change_percentage_24h": 6.4982,
    "market_cap_change_24h": 156719432,
    "market_cap_change_percentage_24h": 6.19047,
    "circulating_supply": 3159107529.0,
    "total_supply": 10000000000.0,
    "max_supply": 10000000000.0,
    "ath": 2.14,
    "ath_change_percentage": -60.0133,
    "ath_date": "2024-12-16T00:36:00.777Z",
    "atl": 0.082171,
    "atl_change_percentage": 941.45998,
    "atl_date": "2024-01-18T12:14:30.524Z",
    "roi": null,
    "last_updated": "2025-03-12T17:38:59.553Z"
  },
  {
    "id": "internet-computer",
    "symbol": "icp",
    "name": "Internet Computer",
    "image": "https://coin-images.coingecko.com/coins/images/14495/large/Internet_Computer_logo.png?1696514180",
    "current_price": 5.46,
    "market_cap": 2626945168,
    "market_cap_rank": 44,
    "fully_diluted_valuation": 2893648686,
    "total_volume": 86390643,
    "high_24h": 5.56,
    "low_24h": 5.27,
    "price_change_24h": 0.173514,
    "price_change_percentage_24h": 3.28374,
    "market_cap_change_24h": 86730268,
    "market_cap_change_percentage_24h": 3.41429,
    "circulating_supply": 481412613.2443532,
    "total_supply": 530288562.0022172,
    "max_supply": null,
    "ath": 700.65,
    "ath_change_percentage": -99.21758,
    "ath_date": "2021-05-10T16:05:53.653Z",
    "atl": 2.87,
    "atl_change_percentage": 91.34194,
    "atl_date": "2023-09-22T00:29:57.369Z",
    "roi": null,
    "last_updated": "2025-03-12T17:38:57.511Z"
  },
  {
    "id": "aave",
    "symbol": "aave",
    "name": "Aave",
    "image": "https://coin-images.coingecko.com/coins/images/12645/large/aave-token-round.png?1720472354",
    "current_price": 171.81,
    "market_cap": 2592309907,
    "market_cap_rank": 45,
    "fully_diluted_valuation": 2748946247,
    "total_volume": 554594084,
    "high_24h": 185.3,
    "low_24h": 164.76,
    "price_change_24h": -0.5001234035083826,
    "price_change_percentage_24h": -0.29024,
    "market_cap_change_24h": -3010686.611729622,
    "market_cap_change_percentage_24h": -0.116,
    "circulating_supply": 15088311.94875699,
    "total_supply": 16000000.0,
    "max_supply": 16000000.0,
    "ath": 661.69,
    "ath_change_percentage": -73.86405,
    "ath_date": "2021-05-18T21:19:59.514Z",
    "atl": 26.02,
    "atl_change_percentage": 564.5583,
    "atl_date": "2020-11-05T09:20:11.928Z",
    "roi": null,
    "last_updated": "2025-03-12T17:38:59.592Z"
  },
  {
    "id": "mantle",
    "symbol": "mnt",
    "name": "Mantle",
    "image": "https://coin-images.coingecko.com/coins/images/30980/large/Mantle-Logo-mark.png?1739213200",
    "current_price": 0.749537,
    "market_cap": 2520262452,
    "market_cap_rank": 46,
    "fully_diluted_valuation": 4658464874,
    "total_volume": 95236921,
    "high_24h": 0.760682,
    "low_24h": 0.704131,
    "price_change_24h": 0.045406,
    "price_change_percentage_24h": 6.44851,
    "market_cap_change_24h": 146960257,
    "market_cap_change_percentage_24h": 6.19223,
    "circulating_supply": 3364694382.83684,
    "total_supply": 6219316794.99,
    "max_supply": 6219316794.99,
    "ath": 1.54,
    "ath_change_percentage": -51.28653,
    "ath_date": "2024-04-08T09:45:25.482Z",
    "atl": 0.307978,
    "atl_change_percentage": 143.38159,
    "atl_date": "2023-10-18T02:50:46.942Z",
    "roi": null,
    "last_updated": "2025-03-12T17:38:57.944Z"
  },
  {
    "id": "okb",
    "symbol": "okb",
    "name": "OKB",
    "image": "https://coin-images.coingecko.com/coins/images/4463/large/WeChat_Image_20220118095654.png?1696505053",
    "current_price": 41.08,
    "market_cap": 2464565316,
    "market_cap_rank": 48,
    "fully_diluted_valuation": 9692218786,
    "total_volume": 9449711,
    "high_24h": 41.67,
    "low_24h": 40.57,
    "price_change_24h": 0.079746,
    "price_change_percentage_24h": 0.1945,
    "market_cap_change_24h": 8354472,
    "market_cap_change_percentage_24h": 0.34014,
    "circulating_supply": 60000000.0,
    "total_supply": 235957685.3,
    "max_supply": 300000000.0,
    "ath": 73.8,
    "ath_change_percentage": -44.15563,
    "ath_date": "2024-03-14T00:30:12.502Z",
    "atl": 0.580608,
    "atl_change_percentage": 6998.59499,
    "atl_date": "2019-01-14T00:00:00.000Z",
    "roi": null,
    "last_updated": "2025-03-12T17:38:58.407Z"
  },
  {
    "id": "gatechain-token",
    "symbol": "gt",
    "name": "Gate",
    "image": "https://coin-images.coingecko.com/coins/images/8183/large/200X200.png?1735246724",
    "current_price": 20.04,
    "market_cap": 2462840068,
    "market_cap_rank": 47,
    "fully_diluted_valuation": 6011296778,
    "total_volume": 28633840,
    "high_24h": 20.39,
    "low_24h": 19.43,
    "price_change_24h": 0.475878,
    "price_change_percentage_24h": 2.43244,
    "market_cap_change_24h": 59805682,
    "market_cap_change_percentage_24h": 2.48876,
    "circulating_supply": 122910587.76765741,
    "total_supply": 300000000.0,
    "max_supply": null,
    "ath": 25.94,
    "ath_change_percentage": -22.54886,
    "ath_date": "2025-01-25T03:07:37.823Z",
    "atl": 0.25754,
    "atl_change_percentage": 7700.87056,
    "atl_date": "2020-03-13T02:18:02.481Z",
    "roi": null,
    "last_updated": "2025-03-12T17:38:55.081Z"
  },
  {
    "id": "coinbase-wrapped-btc",
    "symbol": "cbbtc",
    "name": "Coinbase Wrapped BTC",
    "image": "https://coin-images.coingecko.com/coins/images/40143/large/cbbtc.webp?1726136727",
    "current_price": 82567,
    "market_cap": 2459106963,
    "market_cap_rank": 49,
    "fully_diluted_valuation": 2459106963,
    "total_volume": 355786064,
    "high_24h": 84042,
    "low_24h": 80769,
    "price_change_24h": 1477.81,
    "price_change_percentage_24h": 1.82245,
    "market_cap_change_24h": 62125969,
    "market_cap_change_percentage_24h": 2.59184,
    "circulating_supply": 29681.16152931,
    "total_supply": 30250.07605803,
    "max_supply": null,
    "ath": 108953,
    "ath_change_percentage": -24.19629,
    "ath_date": "2025-01-20T09:20:53.854Z",
    "atl": 57439,
    "atl_change_percentage": 43.78842,
    "atl_date": "2024-09-12T14:07:41.775Z",
    "roi": null,
    "last_updated": "2025-03-12T17:38:52.895Z"
  },
  {
    "id": "crypto-com-chain",
    "symbol": "cro",
    "name": "Cronos",
    "image": "https://coin-images.coingecko.com/coins/images/7310/large/cro_token_logo.png?1696507599",
    "current_price": 0.080576,
    "market_cap": 2205377716,
    "market_cap_rank": 50,
    "fully_diluted_valuation": 2416979589,
    "total_volume": 29844632,
    "high_24h": 0.082382,
    "low_24h": 0.077758,
    "price_change_24h": 0.00102902,
    "price_change_percentage_24h": 1.29359,
    "market_cap_change_24h": 31630670,
    "market_cap_change_percentage_24h": 1.45512,
    "circulating_supply": 27373558223.05747,
    "total_supply": 30000000000.0,
    "max_supply": null,
    "ath": 0.965407,
    "ath_change_percentage": -91.67068,
    "ath_date": "2021-11-24T15:53:54.855Z",
    "atl": 0.0121196,
    "atl_change_percentage": 563.48639,
    "atl_date": "2019-02-08T00:00:00.000Z",
    "roi": null,
    "last_updated": "2025-03-12T17:38:53.119Z"
  },
  {
    "id": "bittensor",
    "symbol": "tao",
    "name": "Bittensor",
    "image": "https://coin-images.coingecko.com/coins/images/28452/large/ARUsPeNQ_400x400.jpeg?1696527447",
    "current_price": 258.45,
    "market_cap": 2189744330,
    "market_cap_rank": 51,
    "fully_diluted_valuation": 5433884210,
    "total_volume": 199061647,
    "high_24h": 270.44,
    "low_24h": 248.67,
    "price_change_24h": 7.71,
    "price_change_percentage_24h": 3.0751,
    "market_cap_change_24h": 66159675,
    "market_cap_change_percentage_24h": 3.11547,
    "circulating_supply": 8462571.0,
    "total_supply": 21000000.0,
    "max_supply": 21000000.0,
    "ath": 757.6,
    "ath_change_percentage": -65.70086,
    "ath_date": "2024-03-07T18:45:36.466Z",
    "atl": 30.83,
    "atl_change_percentage": 742.85513,
    "atl_date": "2023-05-14T08:57:53.732Z",
    "roi": null,
    "last_updated": "2025-03-12T17:39:01.270Z"
  },
  {
    "id": "tokenize-xchange",
    "symbol": "tkx",
    "name": "Tokenize Xchange",
    "image": "https://coin-images.coingecko.com/coins/images/4984/large/TKX_-_Logo_-_RGB-15.png?1696505519",
    "current_price": 26.93,
    "market_cap": 2152548100,
    "market_cap_rank": 52,
    "fully_diluted_valuation": 2690819698,
    "total_volume": 13161781,
    "high_24h": 27.23,
    "low_24h": 26.73,
    "price_change_24h": 0.01073341,
    "price_change_percentage_24h": 0.03988,
    "market_cap_change_24h": 5145643,
    "market_cap_change_percentage_24h": 0.23962,
    "circulating_supply": 79995999.05112354,
    "total_supply": 100000000.0,
    "max_supply": 100000000.0,
    "ath": 50.43,
    "ath_change_percentage": -46.27669,
    "ath_date": "2025-01-03T19:12:43.038Z",
    "atl": 0.111255,
    "atl_change_percentage": 24252.57784,
    "atl_date": "2019-04-28T00:00:00.000Z",
    "roi": {
      "times": 91.68563689568327,
      "currency": "usd",
      "percentage": 9168.563689568327
    },
    "last_updated": "2025-03-12T17:38:54.106Z"
  },
  {
    "id": "official-trump",
    "symbol": "trump",
    "name": "Official Trump",
    "image": "https://coin-images.coingecko.com/coins/images/53746/large/trump.png?1737171561",
    "current_price": 10.38,
    "market_cap": 2076258032,
    "market_cap_rank": 54,
    "fully_diluted_valuation": 10381291343,
    "total_volume": 708127342,
    "high_24h": 10.86,
    "low_24h": 10.08,
    "price_change_24h": 0.0288274,
    "price_change_percentage_24h": 0.27845,
    "market_cap_change_24h": 7933029,
    "market_cap_change_percentage_24h": 0.38355,
    "circulating_supply": 199999977.236,
    "total_supply": 1000000000.0,
    "max_supply": 1000000000.0,
    "ath": 73.43,
    "ath_change_percentage": -85.84865,
    "ath_date": "2025-01-19T11:50:34.806Z",
    "atl": 4.29,
    "atl_change_percentage": 142.18629,
    "atl_date": "2025-01-18T03:40:29.231Z",
    "roi": null,
    "last_updated": "2025-03-12T17:39:00.073Z"
  },
  {
    "id": "first-digital-usd",
    "symbol": "fdusd",
    "name": "First Digital USD",
    "image": "https://coin-images.coingecko.com/coins/images/31079/large/FDUSD_icon_black.png?1731097953",
    "current_price": 0.999213,
    "market_cap": 2076088533,
    "market_cap_rank": 55,
    "fully_diluted_valuation": 2076088533,
    "total_volume": 6601961734,
    "high_24h": 1.004,
    "low_24h": 0.993982,
    "price_change_24h": 0.00433443,
    "price_change_percentage_24h": 0.43567,
    "market_cap_change_24h": 458750,
    "market_cap_change_percentage_24h": 0.0221,
    "circulating_supply": 2077717049.930472,
    "total_supply": 2077717049.930472,
    "max_supply": null,
    "ath": 1.15,
    "ath_change_percentage": -13.29071,
    "ath_date": "2025-02-03T02:30:49.959Z",
    "atl": 0.940377,
    "atl_change_percentage": 6.16084,
    "atl_date": "2024-12-05T22:30:51.394Z",
    "roi": null,
    "last_updated": "2025-03-12T17:38:57.054Z"
  },
  {
    "id": "vechain",
    "symbol": "vet",
    "name": "VeChain",
    "image": "https://coin-images.coingecko.com/coins/images/1167/large/VET_Token_Icon.png?1710013505",
    "current_price": 0.02415062,
    "market_cap": 2075521736,
    "market_cap_rank": 53,
    "fully_diluted_valuation": 2075521736,
    "total_volume": 70551635,
    "high_24h": 0.02501486,
    "low_24h": 0.02305578,
    "price_change_24h": 0.00071183,
    "price_change_percentage_24h": 3.03696,
    "market_cap_change_24h": 63797563,
    "market_cap_change_percentage_24h": 3.17129,
    "circulating_supply": 85985041177.0,
    "total_supply": 85985041177.0,
    "max_supply": 86712634466.0,
    "ath": 0.280991,
    "ath_change_percentage": -91.3752,
    "ath_date": "2021-04-19T01:08:21.675Z",
    "atl": 0.00191713,
    "atl_change_percentage": 1164.12333,
    "atl_date": "2020-03-13T02:29:59.652Z",
    "roi": {
      "times": 3.4884660622203745,
      "currency": "eth",
      "percentage": 348.84660622203745
    },
    "last_updated": "2025-03-12T17:38:55.054Z"
  },
  {
    "id": "ethena",
    "symbol": "ena",
    "name": "Ethena",
    "image": "https://coin-images.coingecko.com/coins/images/36530/large/ethena.png?1711701436",
    "current_price": 0.37081,
    "market_cap": 1960361135,
    "market_cap_rank": 56,
    "fully_diluted_valuation": 5562952082,
    "total_volume": 314804587,
    "high_24h": 0.410717,
    "low_24h": 0.357559,
    "price_change_24h": -0.01097912296737269,
    "price_change_percentage_24h": -2.8757,
    "market_cap_change_24h": -57674545.41813755,
    "market_cap_change_percentage_24h": -2.85795,
    "circulating_supply": 5285937500.0,
    "total_supply": 15000000000.0,
    "max_supply": null,
    "ath": 1.52,
    "ath_change_percentage": -75.51204,
    "ath_date": "2024-04-11T13:15:15.057Z",
    "atl": 0.195078,
    "atl_change_percentage": 90.51576,
    "atl_date": "2024-09-06T21:04:48.253Z",
    "roi": null,
    "last_updated": "2025-03-12T17:38:56.233Z"
  },
  {
    "id": "celestia",
    "symbol": "tia",
    "name": "Celestia",
    "image": "https://coin-images.coingecko.com/coins/images/31967/large/tia.jpg?1696530772",
    "current_price": 3.56,
    "market_cap": 1909064552,
    "market_cap_rank": 57,
    "fully_diluted_valuation": 3924849138,
    "total_volume": 199731597,
    "high_24h": 3.6,
    "low_24h": 2.97,
    "price_change_24h": 0.594041,
    "price_change_percentage_24h": 20.03262,
    "market_cap_change_24h": 310654952,
    "market_cap_change_percentage_24h": 19.43525,
    "circulating_supply": 537233712.821426,
    "total_supply": 1104499726.027065,
    "max_supply": null,
    "ath": 20.85,
    "ath_change_percentage": -82.80554,
    "ath_date": "2024-02-10T14:30:02.495Z",
    "atl": 2.08,
    "atl_change_percentage": 72.07561,
    "atl_date": "2023-10-31T15:14:31.951Z",
    "roi": null,
    "last_updated": "2025-03-12T17:38:52.755Z"
  },
  {
    "id": "polygon-ecosystem-token",
    "symbol": "pol",
    "name": "POL (ex-MATIC)",
    "image": "https://coin-images.coingecko.com/coins/images/32440/large/polygon.png?1698233684",
    "current_price": 0.21634,
    "market_cap": 1860440027,
    "market_cap_rank": 58,
    "fully_diluted_valuation": 2246411398,
    "total_volume": 79209907,
    "high_24h": 0.223564,
    "low_24h": 0.209194,
    "price_change_24h": 0.00687266,
    "price_change_percentage_24h": 3.28101,
    "market_cap_change_24h": 60389684,
    "market_cap_change_percentage_24h": 3.35489,
    "circulating_supply": 8593247931.653555,
    "total_supply": 10376023854.8978,
    "max_supply": null,
    "ath": 1.29,
    "ath_change_percentage": -83.10494,
    "ath_date": "2024-03-13T18:55:06.692Z",
    "atl": 0.194083,
    "atl_change_percentage": 12.08279,
    "atl_date": "2025-03-11T01:10:51.470Z",
    "roi": null,
    "last_updated": "2025-03-12T17:39:00.334Z"
  },
  {
    "id": "kaspa",
    "symbol": "kas",
    "name": "Kaspa",
    "image": "https://coin-images.coingecko.com/coins/images/25751/large/kaspa-icon-exchanges.png?1696524837",
    "current_price": 0.06979,
    "market_cap": 1799238568,
    "market_cap_rank": 60,
    "fully_diluted_valuation": 1800663520,
    "total_volume": 117956865,
    "high_24h": 0.07388,
    "low_24h": 0.06613,
    "price_change_24h": -0.000104165387352209,
    "price_change_percentage_24h": -0.14903,
    "market_cap_change_24h": -18602245.746984005,
    "market_cap_change_percentage_24h": -1.02332,
    "circulating_supply": 25826487850.01926,
    "total_supply": 25846941779.99567,
    "max_supply": 28704026601.0,
    "ath": 0.207411,
    "ath_change_percentage": -66.32977,
    "ath_date": "2024-08-01T00:40:47.164Z",
    "atl": 0.00017105,
    "atl_change_percentage": 40727.79361,
    "atl_date": "2022-05-26T14:42:59.316Z",
    "roi": null,
    "last_updated": "2025-03-12T17:38:57.513Z"
  },
  {
    "id": "filecoin",
    "symbol": "fil",
    "name": "Filecoin",
    "image": "https://coin-images.coingecko.com/coins/images/12817/large/filecoin.png?1696512609",
    "current_price": 2.79,
    "market_cap": 1797139162,
    "market_cap_rank": 59,
    "fully_diluted_valuation": 5474115053,
    "total_volume": 147865571,
    "high_24h": 2.85,
    "low_24h": 2.67,
    "price_change_24h": 0.122685,
    "price_change_percentage_24h": 4.59353,
    "market_cap_change_24h": 83280671,
    "market_cap_change_percentage_24h": 4.85925,
    "circulating_supply": 643335221.0,
    "total_supply": 1959609524.0,
    "max_supply": 1959609549.0,
    "ath": 236.84,
    "ath_change_percentage": -98.81683,
    "ath_date": "2021-04-01T13:29:41.564Z",
    "atl": 2.48,
    "atl_change_percentage": 13.11322,
    "atl_date": "2025-03-11T01:10:57.279Z",
    "roi": null,
    "last_updated": "2025-03-12T17:38:55.510Z"
  },
  {
    "id": "cosmos",
    "symbol": "atom",
    "name": "Cosmos Hub",
    "image": "https://coin-images.coingecko.com/coins/images/1481/large/cosmos_hub.png?1696502525",
    "current_price": 3.93,
    "market_cap": 1727478140,
    "market_cap_rank": 61,
    "fully_diluted_valuation": 1727502389,
    "total_volume": 138075148,
    "high_24h": 3.98,
    "low_24h": 3.76,
    "price_change_24h": 0.145761,
    "price_change_percentage_24h": 3.85374,
    "market_cap_change_24h": 63962239,
    "market_cap_change_percentage_24h": 3.845,
    "circulating_supply": 440012994.616147,
    "total_supply": 440019170.988309,
    "max_supply": null,
    "ath": 44.45,
    "ath_change_percentage": -91.15435,
    "ath_date": "2022-01-17T00:34:41.497Z",
    "atl": 1.16,
    "atl_change_percentage": 238.92376,
    "atl_date": "2020-03-13T02:27:44.591Z",
    "roi": {
      "times": 38.28089287940655,
      "currency": "usd",
      "percentage": 3828.089287940655
    },
    "last_updated": "2025-03-12T17:38:53.917Z"
  },
  {
    "id": "fasttoken",
    "symbol": "ftn",
    "name": "Fasttoken",
    "image": "https://coin-images.coingecko.com/coins/images/28478/large/lightenicon_200x200.png?1696527472",
    "current_price": 3.99,
    "market_cap": 1712372030,
    "market_cap_rank": 62,
    "fully_diluted_valuation": 3471355158,
    "total_volume": 50144540,
    "high_24h": 4.03,
    "low_24h": 3.96,
    "price_change_24h": 0.00856218,
    "price_change_percentage_24h": 0.21527,
    "market_cap_change_24h": 2087404,
    "market_cap_change_percentage_24h": 0.12205,
    "circulating_supply": 429525337.0,
    "total_supply": 870742437.0,
    "max_supply": 1000000000.0,
    "ath": 4.07,
    "ath_change_percentage": -2.02602,
    "ath_date": "2025-03-04T14:41:31.962Z",
    "atl": 0.398142,
    "atl_change_percentage": 902.37326,
    "atl_date": "2023-01-21T10:15:39.503Z",
    "roi": null,
    "last_updated": "2025-03-12T17:38:54.469Z"
  },
  {
    "id": "algorand",
    "symbol": "algo",
    "name": "Algorand",
    "image": "https://coin-images.coingecko.com/coins/images/4380/large/download.png?1696504978",
    "current_price": 0.195096,
    "market_cap": 1658274845,
    "market_cap_rank": 63,
    "fully_diluted_valuation": 1658307180,
    "total_volume": 98592823,
    "high_24h": 0.200545,
    "low_24h": 0.186695,
    "price_change_24h": 0.00504397,
    "price_change_percentage_24h": 2.654,
    "market_cap_change_24h": 45641001,
    "market_cap_change_percentage_24h": 2.83021,
    "circulating_supply": 8485256162.495728,
    "total_supply": 8485421617.830174,
    "max_supply": 10000000000.0,
    "ath": 3.56,
    "ath_change_percentage": -94.49639,
    "ath_date": "2019-06-20T14:51:19.480Z",
    "atl": 0.087513,
    "atl_change_percentage": 123.95622,
    "atl_date": "2023-09-11T19:42:08.247Z",
    "roi": {
      "times": -0.9187101744642109,
      "currency": "usd",
      "percentage": -91.87101744642109
    },
    "last_updated": "2025-03-12T17:38:59.244Z"
  },
  {
    "id": "render-token",
    "symbol": "render",
    "name": "Render",
    "image": "https://coin-images.coingecko.com/coins/images/11636/large/rndr.png?1696511529",
    "current_price": 3.02,
    "market_cap": 1562761405,
    "market_cap_rank": 64,
    "fully_diluted_valuation": 1607315954,
    "total_volume": 243828867,
    "high_24h": 3.16,
    "low_24h": 2.82,
    "price_change_24h": 0.194232,
    "price_change_percentage_24h": 6.88235,
    "market_cap_change_24h": 99495375,
    "market_cap_change_percentage_24h": 6.79954,
    "circulating_supply": 517716590.0562826,
    "total_supply": 532476763.3362826,
    "max_supply": null,
    "ath": 13.53,
    "ath_change_percentage": -77.5227,
    "ath_date": "2024-03-17T16:30:24.636Z",
    "atl": 0.03665669,
    "atl_change_percentage": 8199.25694,
    "atl_date": "2020-06-16T13:22:25.900Z",
    "roi": null,
    "last_updated": "2025-03-12T17:39:01.848Z"
  },
  {
    "id": "story-2",
    "symbol": "ip",
    "name": "Story",
    "image": "https://coin-images.coingecko.com/coins/images/54035/large/Transparent_bg.png?1738075331",
    "current_price": 6.18,
    "market_cap": 1557981526,
    "market_cap_rank": 65,
    "fully_diluted_valuation": 6222505726,
    "total_volume": 191514418,
    "high_24h": 6.59,
    "low_24h": 5.34,
    "price_change_24h": 0.841766,
    "price_change_percentage_24h": 15.7588,
    "market_cap_change_24h": 218979565,
    "market_cap_change_percentage_24h": 16.35394,
    "circulating_supply": 250505371.2,
    "total_supply": 1000506797.52,
    "max_supply": null,
    "ath": 7.31,
    "ath_change_percentage": -14.97829,
    "ath_date": "2025-02-26T16:11:25.410Z",
    "atl": 1.0,
    "atl_change_percentage": 521.62628,
    "atl_date": "2025-02-14T03:11:08.309Z",
    "roi": null,
    "last_updated": "2025-03-12T17:38:52.569Z"
  },
  {
    "id": "arbitrum",
    "symbol": "arb",
    "name": "Arbitrum",
    "image": "https://coin-images.coingecko.com/coins/images/16547/large/arb.jpg?1721358242",
    "current_price": 0.343565,
    "market_cap": 1519834218,
    "market_cap_rank": 66,
    "fully_diluted_valuation": 3439073782,
    "total_volume": 226244986,
    "high_24h": 0.352232,
    "low_24h": 0.327064,
    "price_change_24h": 0.01518813,
    "price_change_percentage_24h": 4.62521,
    "market_cap_change_24h": 72285549,
    "market_cap_change_percentage_24h": 4.99365,
    "circulating_supply": 4419312625.0,
    "total_supply": 10000000000.0,
    "max_supply": 10000000000.0,
    "ath": 2.39,
    "ath_change_percentage": -85.56414,
    "ath_date": "2024-01-12T12:29:59.231Z",
    "atl": 0.301972,
    "atl_change_percentage": 14.26824,
    "atl_date": "2025-03-11T01:11:04.162Z",
    "roi": null,
    "last_updated": "2025-03-12T17:39:00.946Z"
  },
  {
    "id": "arbitrum-bridged-usdt-arbitrum",
    "symbol": "usdt",
    "name": "Arbitrum Bridged USDT (Arbitrum)",
    "image": "https://coin-images.coingecko.com/coins/images/35073/large/logo.png?1707292836",
    "current_price": 0.999979,
    "market_cap": 1449825018,
    "market_cap_rank": 67,
    "fully_diluted_valuation": 1449825018,
    "total_volume": 122368691,
    "high_24h": 1.006,
    "low_24h": 0.991955,
    "price_change_24h": -0.000621233311430047,
    "price_change_percentage_24h": -0.06209,
    "market_cap_change_24h": 18241671,
    "market_cap_change_percentage_24h": 1.27423,
    "circulating_supply": 1451951709.363975,
    "total_supply": 1451951709.363975,
    "max_supply": null,
    "ath": 1.16,
    "ath_change_percentage": -13.84323,
    "ath_date": "2025-02-03T02:27:35.484Z",
    "atl": 0.938168,
    "atl_change_percentage": 6.46973,
    "atl_date": "2024-08-05T01:11:45.298Z",
    "roi": null,
    "last_updated": "2025-03-12T17:38:59.635Z"
  },
  {
    "id": "sonic-3",
    "symbol": "s",
    "name": "Sonic (prev. FTM)",
    "image": "https://coin-images.coingecko.com/coins/images/38108/large/200x200_Sonic_Logo.png?1734679256",
    "current_price": 0.441947,
    "market_cap": 1403412561,
    "market_cap_rank": 68,
    "fully_diluted_valuation": 1403412561,
    "total_volume": 145997999,
    "high_24h": 0.455697,
    "low_24h": 0.411627,
    "price_change_24h": 0.01207159,
    "price_change_percentage_24h": 2.80816,
    "market_cap_change_24h": 39222320,
    "market_cap_change_percentage_24h": 2.87514,
    "circulating_supply": 3175000000.0,
    "total_supply": 3175000000.0,
    "max_supply": null,
    "ath": 1.029,
    "ath_change_percentage": -56.68492,
    "ath_date": "2025-01-04T21:35:44.705Z",
    "atl": 0.359647,
    "atl_change_percentage": 23.98729,
    "atl_date": "2025-02-03T02:11:37.229Z",
    "roi": null,
    "last_updated": "2025-03-12T17:38:52.939Z"
  },
  {
    "id": "jupiter-exchange-solana",
    "symbol": "jup",
    "name": "Jupiter",
    "image": "https://coin-images.coingecko.com/coins/images/34188/large/jup.png?1704266489",
    "current_price": 0.517731,
    "market_cap": 1393265014,
    "market_cap_rank": 69,
    "fully_diluted_valuation": 3624357929,
    "total_volume": 83769642,
    "high_24h": 0.53457,
    "low_24h": 0.500628,
    "price_change_24h": 0.00961925,
    "price_change_percentage_24h": 1.89314,
    "market_cap_change_24h": 29406789,
    "market_cap_change_percentage_24h": 2.15615,
    "circulating_supply": 2690911111.1,
    "total_supply": 6999978412.092612,
    "max_supply": 10000000000.0,
    "ath": 2.0,
    "ath_change_percentage": -74.08895,
    "ath_date": "2024-01-31T15:02:47.304Z",
    "atl": 0.454413,
    "atl_change_percentage": 14.0426,
    "atl_date": "2025-03-11T01:10:59.343Z",
    "roi": null,
    "last_updated": "2025-03-12T17:38:57.929Z"
  },
  {
    "id": "optimism",
    "symbol": "op",
    "name": "Optimism",
    "image": "https://coin-images.coingecko.com/coins/images/25244/large/Optimism.png?1696524385",
    "current_price": 0.849497,
    "market_cap": 1377735382,
    "market_cap_rank": 70,
    "fully_diluted_valuation": 3651081053,
    "total_volume": 156676152,
    "high_24h": 0.877673,
    "low_24h": 0.811603,
    "price_change_24h": 0.01106584,
    "price_change_percentage_24h": 1.31983,
    "market_cap_change_24h": 13918720,
    "market_cap_change_percentage_24h": 1.02057,
    "circulating_supply": 1620705846.0,
    "total_supply": 4294967296.0,
    "max_supply": 4294967296.0,
    "ath": 4.84,
    "ath_change_percentage": -82.35203,
    "ath_date": "2024-03-06T08:35:50.817Z",
    "atl": 0.402159,
    "atl_change_percentage": 112.58314,
    "atl_date": "2022-06-18T20:54:52.178Z",
    "roi": null,
    "last_updated": "2025-03-12T17:38:59.863Z"
  },
  {
    "id": "kucoin-shares",
    "symbol": "kcs",
    "name": "KuCoin",
    "image": "https://coin-images.coingecko.com/coins/images/1047/large/sa9z79.png?1696502152",
    "current_price": 11.02,
    "market_cap": 1349842774,
    "market_cap_rank": 71,
    "fully_diluted_valuation": 1570114226,
    "total_volume": 923981,
    "high_24h": 11.15,
    "low_24h": 10.84,
    "price_change_24h": 0.093942,
    "price_change_percentage_24h": 0.86013,
    "market_cap_change_24h": 14126966,
    "market_cap_change_percentage_24h": 1.05763,
    "circulating_supply": 122561753.8513356,
    "total_supply": 142561753.8513356,
    "max_supply": null,
    "ath": 28.83,
    "ath_change_percentage": -61.80153,
    "ath_date": "2021-12-01T15:09:35.541Z",
    "atl": 0.342863,
    "atl_change_percentage": 3111.94583,
    "atl_date": "2019-02-07T00:00:00.000Z",
    "roi": null,
    "last_updated": "2025-03-12T17:38:58.358Z"
  },
  {
    "id": "fetch-ai",
    "symbol": "fet",
    "name": "Artificial Superintelligence Alliance",
    "image": "https://coin-images.coingecko.com/coins/images/5681/large/ASI.png?1719827289",
    "current_price": 0.500757,
    "market_cap": 1304442593,
    "market_cap_rank": 72,
    "fully_diluted_valuation": 1359292521,
    "total_volume": 221133931,
    "high_24h": 0.514351,
    "low_24h": 0.461824,
    "price_change_24h": 0.03173296,
    "price_change_percentage_24h": 6.76574,
    "market_cap_change_24h": 80974403,
    "market_cap_change_percentage_24h": 6.61843,
    "circulating_supply": 2604959126.672,
    "total_supply": 2714493896.672,
    "max_supply": 2714493896.672,
    "ath": 3.45,
    "ath_change_percentage": -85.37859,
    "ath_date": "2024-03-28T17:21:18.050Z",
    "atl": 0.00816959,
    "atl_change_percentage": 6082.01132,
    "atl_date": "2020-03-13T02:24:18.347Z",
    "roi": {
      "times": 4.775743947052752,
      "currency": "usd",
      "percentage": 477.5743947052752
    },
    "last_updated": "2025-03-12T17:38:55.505Z"
  },
  {
    "id": "solv-btc",
    "symbol": "solvbtc",
    "name": "Solv Protocol SolvBTC",
    "image": "https://coin-images.coingecko.com/coins/images/36800/large/solvBTC.png?1719810684",
    "current_price": 82567,
    "market_cap": 1295335072,
    "market_cap_rank": 73,
    "fully_diluted_valuation": 1295335144,
    "total_volume": 4378768,
    "high_24h": 83657,
    "low_24h": 80742,
    "price_change_24h": 1473.71,
    "price_change_percentage_24h": 1.81731,
    "market_cap_change_24h": 13683825,
    "market_cap_change_percentage_24h": 1.06767,
    "circulating_supply": 15688.23211335432,
    "total_supply": 15688.23298881356,
    "max_supply": 21000000.0,
    "ath": 108929,
    "ath_change_percentage": -24.20903,
    "ath_date": "2025-01-20T07:17:19.296Z",
    "atl": 49058,
    "atl_change_percentage": 68.28836,
    "atl_date": "2024-08-05T06:28:45.311Z",
    "roi": null,
    "last_updated": "2025-03-12T17:38:53.505Z"
  },
  {
    "id": "binance-peg-weth",
    "symbol": "weth",
    "name": "Binance-Peg WETH",
    "image": "https://coin-images.coingecko.com/coins/images/39580/large/weth.png?1723006716",
    "current_price": 1882.9,
    "market_cap": 1139950327,
    "market_cap_rank": 74,
    "fully_diluted_valuation": 1139950327,
    "total_volume": 47868367,
    "high_24h": 1954.33,
    "low_24h": 1827.65,
    "price_change_24h": -12.430049862379974,
    "price_change_percentage_24h": -0.65583,
    "market_cap_change_24h": -6723502.120112181,
    "market_cap_change_percentage_24h": -0.58635,
    "circulating_supply": 604999.999959841,
    "total_supply": 604999.999959841,
    "max_supply": null,
    "ath": 4098.26,
    "ath_change_percentage": -54.02746,
    "ath_date": "2024-12-06T20:27:27.286Z",
    "atl": 1790.63,
    "atl_change_percentage": 5.21856,
    "atl_date": "2025-03-11T01:17:39.749Z",
    "roi": null,
    "last_updated": "2025-03-12T17:39:01.358Z"
  },
  {
    "id": "movement",
    "symbol": "move",
    "name": "Movement",
    "image": "https://coin-images.coingecko.com/coins/images/39345/large/movement-testnet-token.png?1721878759",
    "current_price": 0.465872,
    "market_cap": 1118093561,
    "market_cap_rank": 75,
    "fully_diluted_valuation": 4658723173,
    "total_volume": 97670600,
    "high_24h": 0.508229,
    "low_24h": 0.460213,
    "price_change_24h": -0.025646558390270247,
    "price_change_percentage_24h": -5.21782,
    "market_cap_change_24h": -58520429.162881374,
    "market_cap_change_percentage_24h": -4.97363,
    "circulating_supply": 2400000000.0,
    "total_supply": 10000000000.0,
    "max_supply": 10000000000.0,
    "ath": 1.45,
    "ath_change_percentage": -67.8122,
    "ath_date": "2024-12-10T04:05:51.093Z",
    "atl": 0.378282,
    "atl_change_percentage": 23.36774,
    "atl_date": "2025-03-04T16:40:46.804Z",
    "roi": null,
    "last_updated": "2025-03-12T17:39:00.653Z"
  },
  {
    "id": "quant-network",
    "symbol": "qnt",
    "name": "Quant",
    "image": "https://coin-images.coingecko.com/coins/images/3370/large/5ZOu7brX_400x400.jpg?1696504070",
    "current_price": 75.39,
    "market_cap": 1096116856,
    "market_cap_rank": 76,
    "fully_diluted_valuation": 1101265531,
    "total_volume": 38050640,
    "high_24h": 77.61,
    "low_24h": 72.91,
    "price_change_24h": 2.47,
    "price_change_percentage_24h": 3.39158,
    "market_cap_change_24h": 39278520,
    "market_cap_change_percentage_24h": 3.71661,
    "circulating_supply": 14544176.164091088,
    "total_supply": 14612493.0,
    "max_supply": 14612493.0,
    "ath": 427.42,
    "ath_change_percentage": -82.30775,
    "ath_date": "2021-09-11T09:15:00.668Z",
    "atl": 0.215773,
    "atl_change_percentage": 34946.32875,
    "atl_date": "2018-08-23T00:00:00.000Z",
    "roi": {
      "times": 16.213309529624038,
      "currency": "eth",
      "percentage": 1621.330952962404
    },
    "last_updated": "2025-03-12T17:39:00.185Z"
  },
  {
    "id": "kelp-dao-restaked-eth",
    "symbol": "rseth",
    "name": "Kelp DAO Restaked ETH",
    "image": "https://coin-images.coingecko.com/coins/images/33800/large/Icon___Dark.png?1702991855",
    "current_price": 1955.51,
    "market_cap": 1068604745,
    "market_cap_rank": 77,
    "fully_diluted_valuation": 1068604745,
    "total_volume": 2888523,
    "high_24h": 2029.4,
    "low_24h": 1911.1,
    "price_change_24h": -18.931854876223042,
    "price_change_percentage_24h": -0.95884,
    "market_cap_change_24h": -7823523.367408991,
    "market_cap_change_percentage_24h": -0.7268,
    "circulating_supply": 546489.9670771218,
    "total_supply": 546489.9670771218,
    "max_supply": null,
    "ath": 4216.2,
    "ath_change_percentage": -53.53483,
    "ath_date": "2024-12-06T20:31:16.142Z",
    "atl": 1862.59,
    "atl_change_percentage": 5.17942,
    "atl_date": "2025-03-11T01:10:28.160Z",
    "roi": null,
    "last_updated": "2025-03-12T17:38:56.885Z"
  },
  {
    "id": "nexo",
    "symbol": "nexo",
    "name": "NEXO",
    "image": "https://coin-images.coingecko.com/coins/images/3695/large/CG-nexo-token-200x200_2x.png?1730414360",
    "current_price": 1.058,
    "market_cap": 1057880978,
    "market_cap_rank": 78,
    "fully_diluted_valuation": 1057880978,
    "total_volume": 12573505,
    "high_24h": 1.069,
    "low_24h": 1.004,
    "price_change_24h": 0.04912864,
    "price_change_percentage_24h": 4.86963,
    "market_cap_change_24h": 50081743,
    "market_cap_change_percentage_24h": 4.96942,
    "circulating_supply": 1000000000.0,
    "total_supply": 1000000000.0,
    "max_supply": 1000000000.0,
    "ath": 4.07,
    "ath_change_percentage": -73.99698,
    "ath_date": "2021-05-12T14:37:47.535Z",
    "atl": 0.04515276,
    "atl_change_percentage": 2242.70285,
    "atl_date": "2018-09-13T00:00:00.000Z",
    "roi": {
      "times": 9.58006931762265,
      "currency": "usd",
      "percentage": 958.006931762265
    },
    "last_updated": "2025-03-12T17:39:00.089Z"
  },
  {
    "id": "xdce-crowd-sale",
    "symbol": "xdc",
    "name": "XDC Network",
    "image": "https://coin-images.coingecko.com/coins/images/2912/large/xdc-icon.png?1696503661",
    "current_price": 0.066439,
    "market_cap": 1041179891,
    "market_cap_rank": 79,
    "fully_diluted_valuation": 2519490034,
    "total_volume": 36608369,
    "high_24h": 0.070331,
    "low_24h": 0.065432,
    "price_change_24h": -0.001526254590564186,
    "price_change_percentage_24h": -2.24564,
    "market_cap_change_24h": -22454259.651201725,
    "market_cap_change_percentage_24h": -2.11109,
    "circulating_supply": 15694375491.75,
    "total_supply": 37977896991.3,
    "max_supply": null,
    "ath": 0.192754,
    "ath_change_percentage": -65.41502,
    "ath_date": "2021-08-21T04:39:48.324Z",
    "atl": 0.00039532,
    "atl_change_percentage": 16763.37912,
    "atl_date": "2019-07-22T00:00:00.000Z",
    "roi": {
      "times": 3.6914426411401635,
      "currency": "eth",
      "percentage": 369.1442641140164
    },
    "last_updated": "2025-03-12T17:38:56.316Z"
  },
  {
    "id": "mantra-dao",
    "symbol": "om",
    "name": "MANTRA",
    "image": "https://coin-images.coingecko.com/coins/images/12151/large/OM_Token.png?1696511991",
    "current_price": 6.38,
    "market_cap": 997202828,
    "market_cap_rank": 80,
    "fully_diluted_valuation": 11501880197,
    "total_volume": 90768314,
    "high_24h": 6.44,
    "low_24h": 6.26,
    "price_change_24h": 0.058487,
    "price_change_percentage_24h": 0.9249,
    "market_cap_change_24h": -5109151775.6435,
    "market_cap_change_percentage_24h": -83.66942,
    "circulating_supply": 157057306.7600001,
    "total_supply": 1811533070.83,
    "max_supply": null,
    "ath": 8.99,
    "ath_change_percentage": -29.05826,
    "ath_date": "2025-02-23T01:52:21.073Z",
    "atl": 0.01726188,
    "atl_change_percentage": 36827.46818,
    "atl_date": "2023-10-12T17:25:09.068Z",
    "roi": null,
    "last_updated": "2025-03-12T17:38:58.317Z"
  },
  {
    "id": "dexe",
    "symbol": "dexe",
    "name": "DeXe",
    "image": "https://coin-images.coingecko.com/coins/images/12713/large/DEXE_token_logo.png?1696512514",
    "current_price": 17.34,
    "market_cap": 990084569,
    "market_cap_rank": 81,
    "fully_diluted_valuation": 1673229403,
    "total_volume": 10965021,
    "high_24h": 17.67,
    "low_24h": 17.28,
    "price_change_24h": -0.04150198299787888,
    "price_change_percentage_24h": -0.23879,
    "market_cap_change_24h": -891745.3602099419,
    "market_cap_change_percentage_24h": -0.08999,
    "circulating_supply": 57103774.56313077,
    "total_supply": 96504599.33609451,
    "max_supply": null,
    "ath": 32.38,
    "ath_change_percentage": -46.35832,
    "ath_date": "2021-03-08T13:29:57.935Z",
    "atl": 0.671563,
    "atl_change_percentage": 2486.45576,
    "atl_date": "2020-11-06T19:31:40.144Z",
    "roi": null,
    "last_updated": "2025-03-12T17:38:53.540Z"
  },
  {
    "id": "usual-usd",
    "symbol": "usd0",
    "name": "Usual USD",
    "image": "https://coin-images.coingecko.com/coins/images/38272/large/USD0LOGO.png?1716962811",
    "current_price": 0.99785,
    "market_cap": 978593861,
    "market_cap_rank": 82,
    "fully_diluted_valuation": 978593861,
    "total_volume": 13514873,
    "high_24h": 0.998082,
    "low_24h": 0.997445,
    "price_change_24h": 0.0003345,
    "price_change_percentage_24h": 0.03353,
    "market_cap_change_24h": -2441428.511695385,
    "market_cap_change_percentage_24h": -0.24886,
    "circulating_supply": 980702729.5131422,
    "total_supply": 980702729.5131422,
    "max_supply": null,
    "ath": 1.33,
    "ath_change_percentage": -24.73026,
    "ath_date": "2024-07-12T08:28:59.311Z",
    "atl": 0.976415,
    "atl_change_percentage": 2.19539,
    "atl_date": "2025-01-20T17:07:15.786Z",
    "roi": null,
    "last_updated": "2025-03-12T17:38:56.219Z"
  },
  {
    "id": "maker",
    "symbol": "mkr",
    "name": "Maker",
    "image": "https://coin-images.coingecko.com/coins/images/1364/large/Mark_Maker.png?1696502423",
    "current_price": 1126.57,
    "market_cap": 959224583,
    "market_cap_rank": 83,
    "fully_diluted_valuation": 988769303,
    "total_volume": 102491199,
    "high_24h": 1173.37,
    "low_24h": 1049.52,
    "price_change_24h": -3.03004689200111,
    "price_change_percentage_24h": -0.26824,
    "market_cap_change_24h": -3246269.687669158,
    "market_cap_change_percentage_24h": -0.33728,
    "circulating_supply": 852078.3236894405,
    "total_supply": 878322.8709960858,
    "max_supply": 1005577.0,
    "ath": 6292.31,
    "ath_change_percentage": -82.11294,
    "ath_date": "2021-05-03T21:54:29.333Z",
    "atl": 168.36,
    "atl_change_percentage": 568.52345,
    "atl_date": "2020-03-16T20:52:36.527Z",
    "roi": null,
    "last_updated": "2025-03-12T17:38:58.169Z"
  },
  {
    "id": "blockstack",
    "symbol": "stx",
    "name": "Stacks",
    "image": "https://coin-images.coingecko.com/coins/images/2069/large/Stacks_Logo_png.png?1709979332",
    "current_price": 0.629773,
    "market_cap": 954918637,
    "market_cap_rank": 84,
    "fully_diluted_valuation": 954924932,
    "total_volume": 44580406,
    "high_24h": 0.651279,
    "low_24h": 0.592436,
    "price_change_24h": 0.03093021,
    "price_change_percentage_24h": 5.165,
    "market_cap_change_24h": 46790516,
    "market_cap_change_percentage_24h": 5.15241,
    "circulating_supply": 1516630181.78847,
    "total_supply": 1516640179.78847,
    "max_supply": 1818000000.0,
    "ath": 3.86,
    "ath_change_percentage": -83.69056,
    "ath_date": "2024-04-01T12:34:58.342Z",
    "atl": 0.04559639,
    "atl_change_percentage": 1282.23492,
    "atl_date": "2020-03-13T02:29:26.415Z",
    "roi": {
      "times": 4.248109747493993,
      "currency": "usd",
      "percentage": 424.81097474939935
    },
    "last_updated": "2025-03-12T17:38:51.269Z"
  },
  {
    "id": "rocket-pool-eth",
    "symbol": "reth",
    "name": "Rocket Pool ETH",
    "image": "https://coin-images.coingecko.com/coins/images/20764/large/reth.png?1696520159",
    "current_price": 2110.67,
    "market_cap": 939356377,
    "market_cap_rank": 86,
    "fully_diluted_valuation": 939356377,
    "total_volume": 19158582,
    "high_24h": 2199.53,
    "low_24h": 2065.17,
    "price_change_24h": -15.985213139856114,
    "price_change_percentage_24h": -0.75166,
    "market_cap_change_24h": -6172612.513587356,
    "market_cap_change_percentage_24h": -0.65282,
    "circulating_supply": 442786.9992699565,
    "total_supply": 442783.4919674381,
    "max_supply": null,
    "ath": 4814.31,
    "ath_change_percentage": -55.99164,
    "ath_date": "2021-12-01T08:03:50.749Z",
    "atl": 887.26,
    "atl_change_percentage": 138.79028,
    "atl_date": "2022-06-18T20:55:45.957Z",
    "roi": null,
    "last_updated": "2025-03-12T17:39:00.792Z"
  },
  {
    "id": "injective-protocol",
    "symbol": "inj",
    "name": "Injective",
    "image": "https://coin-images.coingecko.com/coins/images/12882/large/Other_200x200.png?1738782212",
    "current_price": 9.59,
    "market_cap": 936745239,
    "market_cap_rank": 85,
    "fully_diluted_valuation": 958530526,
    "total_volume": 143593712,
    "high_24h": 9.91,
    "low_24h": 8.84,
    "price_change_24h": 0.483847,
    "price_change_percentage_24h": 5.31615,
    "market_cap_change_24h": 48201222,
    "market_cap_change_percentage_24h": 5.42474,
    "circulating_supply": 97727220.33,
    "total_supply": 100000000.0,
    "max_supply": null,
    "ath": 52.62,
    "ath_change_percentage": -81.70477,
    "ath_date": "2024-03-14T15:06:22.124Z",
    "atl": 0.657401,
    "atl_change_percentage": 1364.41474,
    "atl_date": "2020-11-03T16:19:30.576Z",
    "roi": null,
    "last_updated": "2025-03-12T17:38:57.298Z"
  },
  {
    "id": "immutable-x",
    "symbol": "imx",
    "name": "Immutable",
    "image": "https://coin-images.coingecko.com/coins/images/17233/large/immutableX-symbol-BLK-RGB.png?1696516787",
    "current_price": 0.527577,
    "market_cap": 933311125,
    "market_cap_rank": 87,
    "fully_diluted_valuation": 1055592225,
    "total_volume": 34165864,
    "high_24h": 0.536737,
    "low_24h": 0.499547,
    "price_change_24h": 0.01235884,
    "price_change_percentage_24h": 2.39876,
    "market_cap_change_24h": 24115393,
    "market_cap_change_percentage_24h": 2.65239,
    "circulating_supply": 1768317543.3898141,
    "total_supply": 2000000000.0,
    "max_supply": 2000000000.0,
    "ath": 9.52,
    "ath_change_percentage": -94.43641,
    "ath_date": "2021-11-26T01:03:01.536Z",
    "atl": 0.378055,
    "atl_change_percentage": 40.09878,
    "atl_date": "2022-12-31T07:36:37.649Z",
    "roi": null,
    "last_updated": "2025-03-12T17:38:57.604Z"
  },
  {
    "id": "flare-networks",
    "symbol": "flr",
    "name": "Flare",
    "image": "https://coin-images.coingecko.com/coins/images/28624/large/FLR-icon200x200.png?1696527609",
    "current_price": 0.01496964,
    "market_cap": 912224957,
    "market_cap_rank": 88,
    "fully_diluted_valuation": 1543131475,
    "total_volume": 11095176,
    "high_24h": 0.01571767,
    "low_24h": 0.0145964,
    "price_change_24h": 0.00030143,
    "price_change_percentage_24h": 2.05499,
    "market_cap_change_24h": 17247154,
    "market_cap_change_percentage_24h": 1.9271,
    "circulating_supply": 60963544653.60519,
    "total_supply": 103126716595.2674,
    "max_supply": null,
    "ath": 0.150073,
    "ath_change_percentage": -90.00231,
    "ath_date": "2023-01-10T03:14:05.921Z",
    "atl": 0.00827405,
    "atl_change_percentage": 81.33595,
    "atl_date": "2023-10-19T03:35:41.663Z",
    "roi": null,
    "last_updated": "2025-03-12T17:38:54.358Z"
  },
  {
    "id": "worldcoin-wld",
    "symbol": "wld",
    "name": "Worldcoin",
    "image": "https://coin-images.coingecko.com/coins/images/31069/large/worldcoin.jpeg?1696529903",
    "current_price": 0.823496,
    "market_cap": 906466667,
    "market_cap_rank": 89,
    "fully_diluted_valuation": 8240592028,
    "total_volume": 168322920,
    "high_24h": 0.837507,
    "low_24h": 0.775077,
    "price_change_24h": 0.03067373,
    "price_change_percentage_24h": 3.86893,
    "market_cap_change_24h": 37110840,
    "market_cap_change_percentage_24h": 4.26877,
    "circulating_supply": 1100001873.624086,
    "total_supply": 10000000000.0,
    "max_supply": 10000000000.0,
    "ath": 11.74,
    "ath_change_percentage": -92.9598,
    "ath_date": "2024-03-10T00:10:42.330Z",
    "atl": 0.708589,
    "atl_change_percentage": 16.64914,
    "atl_date": "2025-03-11T01:11:28.418Z",
    "roi": null,
    "last_updated": "2025-03-12T17:38:55.992Z"
  },
  {
    "id": "theta-token",
    "symbol": "theta",
    "name": "Theta Network",
    "image": "https://coin-images.coingecko.com/coins/images/2538/large/theta-token-logo.png?1696503349",
    "current_price": 0.88907,
    "market_cap": 889300443,
    "market_cap_rank": 90,
    "fully_diluted_valuation": 889300443,
    "total_volume": 29269370,
    "high_24h": 0.907841,
    "low_24h": 0.834864,
    "price_change_24h": 0.05284,
    "price_change_percentage_24h": 6.31889,
    "market_cap_change_24h": 53108517,
    "market_cap_change_percentage_24h": 6.35124,
    "circulating_supply": 1000000000.0,
    "total_supply": 1000000000.0,
    "max_supply": 1000000000.0,
    "ath": 15.72,
    "ath_change_percentage": -94.30653,
    "ath_date": "2021-04-16T13:15:11.190Z",
    "atl": 0.04039979,
    "atl_change_percentage": 2115.35165,
    "atl_date": "2020-03-13T02:24:16.483Z",
    "roi": {
      "times": 4.927132224693785,
      "currency": "usd",
      "percentage": 492.7132224693785
    },
    "last_updated": "2025-03-12T17:38:56.143Z"
  },
  {
    "id": "the-graph",
    "symbol": "grt",
    "name": "The Graph",
    "image": "https://coin-images.coingecko.com/coins/images/13397/large/Graph_Token.png?1696513159",
    "current_price": 0.09077,
    "market_cap": 869871367,
    "market_cap_rank": 91,
    "fully_diluted_valuation": 982787359,
    "total_volume": 49883788,
    "high_24h": 0.094362,
    "low_24h": 0.087686,
    "price_change_24h": 0.00222698,
    "price_change_percentage_24h": 2.51515,
    "market_cap_change_24h": 19009763,
    "market_cap_change_percentage_24h": 2.23418,
    "circulating_supply": 9548531509.16547,
    "total_supply": 10788004319.0,
    "max_supply": 10788004319.0,
    "ath": 2.84,
    "ath_change_percentage": -96.78677,
    "ath_date": "2021-02-12T07:28:45.775Z",
    "atl": 0.052051,
    "atl_change_percentage": 75.41273,
    "atl_date": "2022-11-22T10:05:03.503Z",
    "roi": null,
    "last_updated": "2025-03-12T17:38:54.624Z"
  },
  {
    "id": "sei-network",
    "symbol": "sei",
    "name": "Sei",
    "image": "https://coin-images.coingecko.com/coins/images/28205/large/Sei_Logo_-_Transparent.png?1696527207",
    "current_price": 0.183996,
    "market_cap": 857600222,
    "market_cap_rank": 92,
    "fully_diluted_valuation": 1841331662,
    "total_volume": 100207433,
    "high_24h": 0.197606,
    "low_24h": 0.178346,
    "price_change_24h": -0.005131004235825964,
    "price_change_percentage_24h": -2.713,
    "market_cap_change_24h": -27764076.37764132,
    "market_cap_change_percentage_24h": -3.13589,
    "circulating_supply": 4657499999.0,
    "total_supply": 10000000000.0,
    "max_supply": null,
    "ath": 1.14,
    "ath_change_percentage": -83.74724,
    "ath_date": "2024-03-16T02:30:23.904Z",
    "atl": 0.095364,
    "atl_change_percentage": 94.2411,
    "atl_date": "2023-10-19T08:05:30.655Z",
    "roi": null,
    "last_updated": "2025-03-12T17:39:01.253Z"
  },
  {
    "id": "polygon-bridged-usdt-polygon",
    "symbol": "usdt",
    "name": "Polygon Bridged USDT (Polygon)",
    "image": "https://coin-images.coingecko.com/coins/images/35023/large/USDT.png?1707233644",
    "current_price": 0.99912,
    "market_cap": 847043878,
    "market_cap_rank": 93,
    "fully_diluted_valuation": 844299402,
    "total_volume": 13584574,
    "high_24h": 1.003,
    "low_24h": 0.996085,
    "price_change_24h": -0.001757498535440827,
    "price_change_percentage_24h": -0.1756,
    "market_cap_change_24h": 4077978,
    "market_cap_change_percentage_24h": 0.48377,
    "circulating_supply": 847913110.465269,
    "total_supply": 845165818.01636,
    "max_supply": null,
    "ath": 1.027,
    "ath_change_percentage": -2.74505,
    "ath_date": "2024-04-14T06:51:56.926Z",
    "atl": 0.945933,
    "atl_change_percentage": 5.5675,
    "atl_date": "2024-12-05T22:30:30.789Z",
    "roi": null,
    "last_updated": "2025-03-12T17:39:00.503Z"
  },
  {
    "id": "binance-staked-sol",
    "symbol": "bnsol",
    "name": "Binance Staked SOL",
    "image": "https://coin-images.coingecko.com/coins/images/40132/large/bnsol.png?1725968367",
    "current_price": 130.27,
    "market_cap": 845128504,
    "market_cap_rank": 94,
    "fully_diluted_valuation": 845128504,
    "total_volume": 3649907,
    "high_24h": 135.44,
    "low_24h": 126.13,
    "price_change_24h": 1.73,
    "price_change_percentage_24h": 1.34593,
    "market_cap_change_24h": 5848753,
    "market_cap_change_percentage_24h": 0.69688,
    "circulating_supply": 6466869.198561981,
    "total_supply": 6466869.396350435,
    "max_supply": null,
    "ath": 297.96,
    "ath_change_percentage": -56.22331,
    "ath_date": "2025-01-19T11:30:53.744Z",
    "atl": 118.29,
    "atl_change_percentage": 10.26394,
    "atl_date": "2025-03-11T01:11:46.882Z",
    "roi": null,
    "last_updated": "2025-03-12T17:39:00.996Z"
  },
  {
    "id": "solv-protocol-solvbtc-bbn",
    "symbol": "solvbtc.bbn",
    "name": "Solv Protocol SolvBTC.BBN",
    "image": "https://coin-images.coingecko.com/coins/images/39384/large/unnamed.png?1721961640",
    "current_price": 81982,
    "market_cap": 817916045,
    "market_cap_rank": 95,
    "fully_diluted_valuation": 817916045,
    "total_volume": 1006980,
    "high_24h": 83277,
    "low_24h": 80464,
    "price_change_24h": 1143.14,
    "price_change_percentage_24h": 1.41409,
    "market_cap_change_24h": 11836661,
    "market_cap_change_percentage_24h": 1.46842,
    "circulating_supply": 9976.721646418193,
    "total_supply": 9976.721646418193,
    "max_supply": 21000000.0,
    "ath": 117077,
    "ath_change_percentage": -30.52708,
    "ath_date": "2025-01-20T07:15:49.114Z",
    "atl": 11402.13,
    "atl_change_percentage": 613.34496,
    "atl_date": "2024-09-10T17:58:43.974Z",
    "roi": null,
    "last_updated": "2025-03-12T17:38:51.632Z"
  },
  {
    "id": "lido-dao",
    "symbol": "ldo",
    "name": "Lido DAO",
    "image": "https://coin-images.coingecko.com/coins/images/13573/large/Lido_DAO.png?1696513326",
    "current_price": 0.90238,
    "market_cap": 814105407,
    "market_cap_rank": 96,
    "fully_diluted_valuation": 906977453,
    "total_volume": 141702222,
    "high_24h": 0.970207,
    "low_24h": 0.878439,
    "price_change_24h": 0.00287748,
    "price_change_percentage_24h": 0.3199,
    "market_cap_change_24h": 2235441,
    "market_cap_change_percentage_24h": 0.27534,
    "circulating_supply": 897602695.87191,
    "total_supply": 1000000000.0,
    "max_supply": 1000000000.0,
    "ath": 7.3,
    "ath_change_percentage": -87.56374,
    "ath_date": "2021-08-20T08:35:20.158Z",
    "atl": 0.40615,
    "atl_change_percentage": 123.61302,
    "atl_date": "2022-06-18T20:55:12.035Z",
    "roi": null,
    "last_updated": "2025-03-12T17:38:58.090Z"
  },
  {
    "id": "bonk",
    "symbol": "bonk",
    "name": "Bonk",
    "image": "https://coin-images.coingecko.com/coins/images/28600/large/bonk.jpg?1696527587",
    "current_price": 1.048e-5,
    "market_cap": 811886788,
    "market_cap_rank": 97,
    "fully_diluted_valuation": 931828778,
    "total_volume": 98162835,
    "high_24h": 1.077e-5,
    "low_24h": 1.009e-5,
    "price_change_24h": 3.41466e-7,
    "price_change_percentage_24h": 3.36763,
    "market_cap_change_24h": 26943274,
    "market_cap_change_percentage_24h": 3.43251,
    "circulating_supply": 77419592329436.58,
    "total_supply": 88856975109660.95,
    "max_supply": 88857053645673.19,
    "ath": 5.825e-5,
    "ath_change_percentage": -81.93118,
    "ath_date": "2024-11-20T04:01:06.465Z",
    "atl": 8.6142e-8,
    "atl_change_percentage": 12118.26847,
    "atl_date": "2022-12-29T22:48:46.755Z",
    "roi": null,
    "last_updated": "2025-03-12T17:38:52.179Z"
  },
  {
    "id": "eos",
    "symbol": "eos",
    "name": "EOS",
    "image": "https://coin-images.coingecko.com/coins/images/738/large/CG_EOS_Icon.png?1731705232",
    "current_price": 0.494687,
    "market_cap": 750606165,
    "market_cap_rank": 98,
    "fully_diluted_valuation": 1039150712,
    "total_volume": 92389527,
    "high_24h": 0.504346,
    "low_24h": 0.47285,
    "price_change_24h": 0.01696034,
    "price_change_percentage_24h": 3.55022,
    "market_cap_change_24h": 25090318,
    "market_cap_change_percentage_24h": 3.45827,
    "circulating_supply": 1516885789.1746,
    "total_supply": 2100000000.0,
    "max_supply": 2100000000.0,
    "ath": 22.71,
    "ath_change_percentage": -97.81143,
    "ath_date": "2018-04-29T07:50:33.540Z",
    "atl": 0.402746,
    "atl_change_percentage": 23.4158,
    "atl_date": "2024-11-04T21:55:59.771Z",
    "roi": {
      "times": -0.500315778446924,
      "currency": "usd",
      "percentage": -50.03157784469239
    },
    "last_updated": "2025-03-12T17:38:54.995Z"
  },
  {
    "id": "mantle-staked-ether",
    "symbol": "meth",
    "name": "Mantle Staked Ether",
    "image": "https://coin-images.coingecko.com/coins/images/33345/large/symbol_transparent_bg.png?1701697066",
    "current_price": 1997.22,
    "market_cap": 750518175,
    "market_cap_rank": 99,
    "fully_diluted_valuation": 750518175,
    "total_volume": 9195654,
    "high_24h": 2071.4,
    "low_24h": 1952.68,
    "price_change_24h": -11.182415423818384,
    "price_change_percentage_24h": -0.55678,
    "market_cap_change_24h": -1467173.9899874926,
    "market_cap_change_percentage_24h": -0.19511,
    "circulating_supply": 375480.9506124179,
    "total_supply": 375480.9506124179,
    "max_supply": null,
    "ath": 4729.53,
    "ath_change_percentage": -57.66996,
    "ath_date": "2024-03-27T05:26:27.333Z",
    "atl": 1896.19,
    "atl_change_percentage": 5.58045,
    "atl_date": "2025-03-11T00:57:41.551Z",
    "roi": null,
    "last_updated": "2025-03-12T17:38:59.112Z"
  },
  {
    "id": "tether-gold",
    "symbol": "xaut",
    "name": "Tether Gold",
    "image": "https://coin-images.coingecko.com/coins/images/10481/large/Tether_Gold.png?1696510471",
    "current_price": 2922.56,
    "market_cap": 720481660,
    "market_cap_rank": 101,
    "fully_diluted_valuation": 720481660,
    "total_volume": 13913079,
    "high_24h": 2923.56,
    "low_24h": 2903.63,
    "price_change_24h": 14.62,
    "price_change_percentage_24h": 0.50286,
    "market_cap_change_24h": 3135438,
    "market_cap_change_percentage_24h": 0.43709,
    "circulating_supply": 246524.33,
    "total_supply": 246524.33,
    "max_supply": null,
    "ath": 2958.51,
    "ath_change_percentage": -1.22776,
    "ath_date": "2025-02-24T22:27:43.675Z",
    "atl": 1447.84,
    "atl_change_percentage": 101.83037,
    "atl_date": "2020-03-19T13:45:41.821Z",
    "roi": null,
    "last_updated": "2025-03-12T17:38:53.787Z"
  }
]
